Workbook
Name LIST_THERAPIST: VALIDATION!$D$2:$D$5
Name LIST_SERVICE: VALIDATION!$C$2:$C$92
Name LIST_AREA: VALIDATION!$F$2:$F$4
Name LIST_BOOKING_TYPE: VALIDATION!$A$2:$A$3
Name LIST_STATUS: VALIDATION!$B$2:$B$5
Name LIST_PAYMENT: VALIDATION!$E$2:$E$4
Name LIST_PROMO: VALIDATION!$G$2:$G$6

Sheet LOGIN
B1: DASHBOARD | D1: INPUT | F1: LOG | H1: CRM | J1: HARIAN | L1: BULANAN | N1: INVOICE | P1: JADWAL | R1: LOGIN
B6: Nama Email | C6: puguh.legowo.k@gmail.com | E6: PIN | F6: 1234 | H6: LOGIN
B8: Role | C8: OWNER | E8: Status | F8: LOGIN OK | H8: LOGOUT
B9: Tanggal Login | C9: 46107.78

Sheet START HERE
B2: START HERE - 5 LANGKAH CEPAT (VERSI PREMIUM)
B4: No | C4: Langkah
B5: 1 | C5: Pilih Menu SmartSpaDash Premium, klik Otorisasi Akun Google
B6: 2 | C6: Login di sheet login
B7: 3 | C7: Isi semua master layanan, terapis, SA ( Sheet Warna Kuning )
B8: 4 | C8: Input Booking
B9: 5 | C9: Pantau hasil di DASHBOARD, JADWAL HARIAN, REKAP, dan KOMISI TERAPIS.

Sheet DASHBOARD V2
B1: DASHBOARD | D1: INPUT | F1: LOG | H1: CRM | J1: HARIAN | L1: BULANAN | N1: INVOICE | P1: JADWAL | R1: LOGIN
B5: Tahun | C5: Semua Tahun | E5: Bulan | F5: Maret | H5: Hari | I5: Semua Hari | K5: RESET FILTER
B7: Total Booking Closed | E7: Omzet Closed | H7: Homecare Closed
B8: ='DASHBOARD V2 DATA'!$S$2 -> 4 | E8: ='DASHBOARD V2 DATA'!$T$2 -> 370000 | H8: ='DASHBOARD V2 DATA'!$U$2 -> 1
B12: Inhouse Closed | E12: Avg Ticket Closed | H12: Filter Aktif
B13: ='DASHBOARD V2 DATA'!$V$2 -> 3 | E13: ='DASHBOARD V2 DATA'!$W$2 -> 92500 | H13: =IF(C5="Semua Tahun","Semua Tahun",C5)&" | "&IF(F5="Semua Bulan","Semua Bulan",F5)&" | "&IF(I5="Semua Hari","Semua Hari",I5) -> Semua Tahun | Maret | Semua Hari
B18: Filter Ringkas | E18: 10 Layanan Terlaris (Closed Booking)
B19: Year | C19: =C5 -> Semua Tahun | E19: Ranking | F19: Layanan | G19: Category | H19: Inhouse/Homecare | I19: Jumlah Booking
B20: Month | C20: =F5 -> Maret | E20: =IF('DASHBOARD V2 DATA'!$A$2="" ,"" ,'DASHBOARD V2 DATA'!$A$2) -> 1 | F20: =IF($E20="" ,"" ,'DASHBOARD V2 DATA'!$B$2) -> Colic Relief Massage Baby (Pijat Kolik) | G20: =IF($E20="" ,"" ,'DASHBOARD V2 DATA'!$C$2) -> BABY | H20: =IF($E20="" ,"" ,'DASHBOARD V2 DATA'!$D$2) -> Inhouse | I20: =IF($E20="" ,"" ,'DASHBOARD V2 DATA'!$E$2) -> 1
B21: Day | C21: =I5 -> Semua Hari | E21: =IF('DASHBOARD V2 DATA'!$A$3="" ,"" ,'DASHBOARD V2 DATA'!$A$3) -> 2 | F21: =IF($E21="" ,"" ,'DASHBOARD V2 DATA'!$B$3) -> Healthy Breath Package (Paket Nafas Sehat) | G21: =IF($E21="" ,"" ,'DASHBOARD V2 DATA'!$C$3) -> BABY | H21: =IF($E21="" ,"" ,'DASHBOARD V2 DATA'!$D$3) -> Inhouse | I21: =IF($E21="" ,"" ,'DASHBOARD V2 DATA'!$E$3) -> 1
E22: =IF('DASHBOARD V2 DATA'!$A$4="" ,"" ,'DASHBOARD V2 DATA'!$A$4) -> 3 | F22: =IF($E22="" ,"" ,'DASHBOARD V2 DATA'!$B$4) -> Newborn Starter Pack With Piercing (Paket Awal Kehidupan) | G22: =IF($E22="" ,"" ,'DASHBOARD V2 DATA'!$C$4) -> BABY | H22: =IF($E22="" ,"" ,'DASHBOARD V2 DATA'!$D$4) -> Inhouse | I22: =IF($E22="" ,"" ,'DASHBOARD V2 DATA'!$E$4) -> 1
E23: =IF('DASHBOARD V2 DATA'!$A$5="" ,"" ,'DASHBOARD V2 DATA'!$A$5) -> 4 | F23: =IF($E23="" ,"" ,'DASHBOARD V2 DATA'!$B$5) -> Oxytocin Stimulation Massage HC (Pijat Oksitosin) | G23: =IF($E23="" ,"" ,'DASHBOARD V2 DATA'!$C$5) -> HOMECARE MOM | H23: =IF($E23="" ,"" ,'DASHBOARD V2 DATA'!$D$5) -> Homecare | I23: =IF($E23="" ,"" ,'DASHBOARD V2 DATA'!$E$5) -> 1
E24: =IF('DASHBOARD V2 DATA'!$A$6="" ,"" ,'DASHBOARD V2 DATA'!$A$6) | F24: =IF($E24="" ,"" ,'DASHBOARD V2 DATA'!$B$6) | G24: =IF($E24="" ,"" ,'DASHBOARD V2 DATA'!$C$6) | H24: =IF($E24="" ,"" ,'DASHBOARD V2 DATA'!$D$6) | I24: =IF($E24="" ,"" ,'DASHBOARD V2 DATA'!$E$6)
E25: =IF('DASHBOARD V2 DATA'!$A$7="" ,"" ,'DASHBOARD V2 DATA'!$A$7) | F25: =IF($E25="" ,"" ,'DASHBOARD V2 DATA'!$B$7) | G25: =IF($E25="" ,"" ,'DASHBOARD V2 DATA'!$C$7) | H25: =IF($E25="" ,"" ,'DASHBOARD V2 DATA'!$D$7) | I25: =IF($E25="" ,"" ,'DASHBOARD V2 DATA'!$E$7)
E26: =IF('DASHBOARD V2 DATA'!$A$8="" ,"" ,'DASHBOARD V2 DATA'!$A$8) | F26: =IF($E26="" ,"" ,'DASHBOARD V2 DATA'!$B$8) | G26: =IF($E26="" ,"" ,'DASHBOARD V2 DATA'!$C$8) | H26: =IF($E26="" ,"" ,'DASHBOARD V2 DATA'!$D$8) | I26: =IF($E26="" ,"" ,'DASHBOARD V2 DATA'!$E$8)
E27: =IF('DASHBOARD V2 DATA'!$A$9="" ,"" ,'DASHBOARD V2 DATA'!$A$9) | F27: =IF($E27="" ,"" ,'DASHBOARD V2 DATA'!$B$9) | G27: =IF($E27="" ,"" ,'DASHBOARD V2 DATA'!$C$9) | H27: =IF($E27="" ,"" ,'DASHBOARD V2 DATA'!$D$9) | I27: =IF($E27="" ,"" ,'DASHBOARD V2 DATA'!$E$9)
E28: =IF('DASHBOARD V2 DATA'!$A$10="" ,"" ,'DASHBOARD V2 DATA'!$A$10) | F28: =IF($E28="" ,"" ,'DASHBOARD V2 DATA'!$B$10) | G28: =IF($E28="" ,"" ,'DASHBOARD V2 DATA'!$C$10) | H28: =IF($E28="" ,"" ,'DASHBOARD V2 DATA'!$D$10) | I28: =IF($E28="" ,"" ,'DASHBOARD V2 DATA'!$E$10)
E29: =IF('DASHBOARD V2 DATA'!$A$11="" ,"" ,'DASHBOARD V2 DATA'!$A$11) | F29: =IF($E29="" ,"" ,'DASHBOARD V2 DATA'!$B$11) | G29: =IF($E29="" ,"" ,'DASHBOARD V2 DATA'!$C$11) | H29: =IF($E29="" ,"" ,'DASHBOARD V2 DATA'!$D$11) | I29: =IF($E29="" ,"" ,'DASHBOARD V2 DATA'!$E$11)
B31: Trend Omzet Closed | J31: Trend Booking Closed | R31: Homecare vs Inhouse
B60: Dashboard V2 mengambil omzet hanya dari payment_status = Lunas dan service_done_status = DONE.

Sheet INPUT BOOKING
B1: DASHBOARD | D1: INPUT | F1: LOG | H1: CRM | J1: HARIAN | L1: BULANAN | N1: INVOICE | P1: JADWAL | R1: LOGIN
C4: PILIH TANGGAL BOOKING: | D4: BULAN | E4: TAHUN
B5: INFORMASI BOOKING | C5: 26 | D5: 3 | E5: 2026 | H5: RINGKASAN PEMBAYARAN | J5: HASIL BOOKING | K5: HASIL CARI
B6: Tanggal Booking | C6: =D5&"/"&C5&"/"&E5 -> 3/26/2026 | E6: Jenis Booking | H6: Kode Booking Aktif
B7: Terapis | E7: Status Booking | H7: Kategori | J7: {=IFERROR(XLOOKUP(C8,MASTER_LAYANAN!$C:$C,MASTER_LAYANAN!$B:$B,""),"")}
B8: Layanan | E8: Area Homecare | H8: Durasi (menit) | J8: {=IFERROR(XLOOKUP(C8,MASTER_LAYANAN!$C:$C,MASTER_LAYANAN!$D:$D,0),0)} -> 0
B9: Jam Mulai | E9: Promo / Diskon | H9: Harga Layanan | J9: {=IFERROR(XLOOKUP(C8,MASTER_LAYANAN!$C:$C,MASTER_LAYANAN!$E:$E,0),0)} -> 0
H10: Nilai Diskon | J10: {=IFERROR(IF(F9="","",IF(XLOOKUP(F9,MASTER_PROMO!$A:$A,MASTER_PROMO!$C:$C,"")="PERCENT",J9*XLOOKUP(F9,MASTER_PROMO!$A:$A,MASTER_PROMO!$D:$D,0)/100,_xludf.XLOOKUP(F9,MASTER_PROMO!$A:$A,MASTER_PROMO!$D:$D,0))),0)}
B11: DATA PELANGGAN | H11: Biaya Transport | J11: {=IF(F6="Homecare",IFERROR(XLOOKUP(F8,MASTER_HOMECARE!$A:$A,MASTER_HOMECARE!$C:$C,0),0),0)} -> 0
B12: Nama Mama / Ortu | E12: No WhatsApp | H12: Grand Total | J12: =J9-J10+J11 -> 0
B13: Nama Anak | E13: Usia Anak/ Mama | H13: Fee Terapis | J13: {=IFERROR(XLOOKUP(C8,MASTER_LAYANAN!$C:$C,MASTER_LAYANAN!$F:$F,0),0)*1000} -> 0
B14: Alamat | E14: Berat Anak/ Mama | H14: Fee Admin | J14: {=IFERROR(XLOOKUP(C8,MASTER_LAYANAN!$C:$C,MASTER_LAYANAN!$G:$G,0),0)*1000} -> 0
B15: Catatan Booking | E15: Metode Bayar | H15: Sisa Bayar | J15: =MAX(0,J12-C16) -> 0
B16: Deposit | E16: Cari Booking / WA | H16: Nama Ibu / Ortu
H17: Tanggal Booking
B18: KODE BOOKING BELUM LUNAS / BELUM SELESAI | H18: SIMPAN BOOKING | J18: RESET FORM
B19: Booking_ID | C19: Payment_Status | D19: service_done status
H20: CEK BENTROK | J20: CARI BOOKING
H22: BATAL DONE /LUNAS | J22: BUAT INVOICE
H24: TANDAI LUNAS | J24: TANDAI SELESAI
H26: Panduan Cepat | J26: Isi No WA / kode booking di F16 lalu klik Cari Booking. J22/H24/J24 akan memproses hasil di K6:K17.
H27: Status Sistem | J27: SmartSpaDash : Form berhasil di-reset.

Sheet JADWAL HARIAN
B1: DASHBOARD | D1: INPUT | F1: LOG | H1: CRM | J1: HARIAN | L1: BULANAN | N1: INVOICE | P1: JADWAL | R1: LOGIN
D4: PILIH TANGGAL | E4: PILIH BULAN | F4: PILIH TAHUN
B5: Tanggal Jadwal | C5: =D5&"-"&E5&"-"&F5 -> 26-3-2026 | D5: 26 | E5: 3 | F5: 2026
B7: Jam | C7: =IF(MASTER_TERAPIS!D2="YA",MASTER_TERAPIS!B2) -> bababab | D7: =IF(MASTER_TERAPIS!D3="YA",MASTER_TERAPIS!B3) -> Caccaca | E7: =IF(MASTER_TERAPIS!D4="YA",MASTER_TERAPIS!B4) -> ggagaga | F7: =IF(MASTER_TERAPIS!D5="YA",MASTER_TERAPIS!B5) -> hahaha | G7: =IF(MASTER_TERAPIS!D6="YA",MASTER_TERAPIS!B6) -> FALSE | H7: =IF(MASTER_TERAPIS!D7="YA",MASTER_TERAPIS!B7) -> FALSE
B8: 0.33333333 | C8: {=IFERROR(INDEX(TRANSAKSI_LOG!$M$2:$M$998,MATCH(1,INDEX((TRANSAKSI_LOG!$C$2:$C$998=$C$5)*(TRANSAKSI_LOG!$J$2:$J$998=C$7)*(TRANSAKSI_LOG!$E$2:$E$998<=$B8)*(TRANSAKSI_LOG!$F$2:$F$998>=$B8),0),0)) & " - " & INDEX(TRANSAKSI_LOG!$H$2:$H$998,MATCH(1,INDEX((TRANSAKSI_LOG!$C$2:$C$998=$C$5)*(TRANSAKSI_LOG!$J$2:$J$998=C$7)*(TRANSAKSI_LOG!$E$2:$E$998<=$B8)*(TRANSAKSI_LOG!$F$2:$F$998>=$B8),0),0)),"")} | D8: {=IFERROR(INDEX(TRANSAKSI_LOG!$M$2:$M$998,MATCH(1,INDEX((TRANSAKSI_LOG!$C$2:$C$998=$C$5)*(TRANSAKSI_LOG!$J$2:$J$998=D$7)*(TRANSAKSI_LOG!$E$2:$E$998<=$B8)*(TRANSAKSI_LOG!$F$2:$F$998>=$B8),0),0)) & " - " & INDEX(TRANSAKSI_LOG!$H$2:$H$998,MATCH(1,INDEX((TRANSAKSI_LOG!$C$2:$C$998=$C$5)*(TRANSAKSI_LOG!$J$2:$J$998=D$7)*(TRANSAKSI_LOG!$E$2:$E$998<=$B8)*(TRANSAKSI_LOG!$F$2:$F$998>=$B8),0),0)),"")} | E8: {=IFERROR(INDEX(TRANSAKSI_LOG!$M$2:$M$998,MATCH(1,INDEX((TRANSAKSI_LOG!$C$2:$C$998=$C$5)*(TRANSAKSI_LOG!$J$2:$J$998=E$7)*(TRANSAKSI_LOG!$E$2:$E$998<=$B8)*(TRANSAKSI_LOG!$F$2:$F$998>=$B8),0),0)) & " - " & INDEX(TRANSAKSI_LOG!$H$2:$H$998,MATCH(1,INDEX((TRANSAKSI_LOG!$C$2:$C$998=$C$5)*(TRANSAKSI_LOG!$J$2:$J$998=E$7)*(TRANSAKSI_LOG!$E$2:$E$998<=$B8)*(TRANSAKSI_LOG!$F$2:$F$998>=$B8),0),0)),"")} | F8: {=IFERROR(INDEX(TRANSAKSI_LOG!$M$2:$M$998,MATCH(1,INDEX((TRANSAKSI_LOG!$C$2:$C$998=$C$5)*(TRANSAKSI_LOG!$J$2:$J$998=F$7)*(TRANSAKSI_LOG!$E$2:$E$998<=$B8)*(TRANSAKSI_LOG!$F$2:$F$998>=$B8),0),0)) & " - " & INDEX(TRANSAKSI_LOG!$H$2:$H$998,MATCH(1,INDEX((TRANSAKSI_LOG!$C$2:$C$998=$C$5)*(TRANSAKSI_LOG!$J$2:$J$998=F$7)*(TRANSAKSI_LOG!$E$2:$E$998<=$B8)*(TRANSAKSI_LOG!$F$2:$F$998>=$B8),0),0)),"")} | G8: {=IFERROR(INDEX(TRANSAKSI_LOG!$M$2:$M$998,MATCH(1,INDEX((TRANSAKSI_LOG!$C$2:$C$998=$C$5)*(TRANSAKSI_LOG!$J$2:$J$998=G$7)*(TRANSAKSI_LOG!$E$2:$E$998<=$B8)*(TRANSAKSI_LOG!$F$2:$F$998>=$B8),0),0)) & " - " & INDEX(TRANSAKSI_LOG!$H$2:$H$998,MATCH(1,INDEX((TRANSAKSI_LOG!$C$2:$C$998=$C$5)*(TRANSAKSI_LOG!$J$2:$J$998=G$7)*(TRANSAKSI_LOG!$E$2:$E$998<=$B8)*(TRANSAKSI_LOG!$F$2:$F$998>=$B8),0),0)),"")} | H8: {=IFERROR(INDEX(TRANSAKSI_LOG!$M$2:$M$998,MATCH(1,INDEX((TRANSAKSI_LOG!$C$2:$C$998=$C$5)*(TRANSAKSI_LOG!$J$2:$J$998=H$7)*(TRANSAKSI_LOG!$E$2:$E$998<=$B8)*(TRANSAKSI_LOG!$F$2:$F$998>=$B8),0),0)) & " - " & INDEX(TRANSAKSI_LOG!$H$2:$H$998,MATCH(1,INDEX((TRANSAKSI_LOG!$C$2:$C$998=$C$5)*(TRANSAKSI_LOG!$J$2:$J$998=H$7)*(TRANSAKSI_LOG!$E$2:$E$998<=$B8)*(TRANSAKSI_LOG!$F$2:$F$998>=$B8),0),0)),"")}
B9: 0.33680556 | C9: {=IFERROR(INDEX(TRANSAKSI_LOG!$M$2:$M$998,MATCH(1,INDEX((TRANSAKSI_LOG!$C$2:$C$998=$C$5)*(TRANSAKSI_LOG!$J$2:$J$998=C$7)*(TRANSAKSI_LOG!$E$2:$E$998<=$B9)*(TRANSAKSI_LOG!$F$2:$F$998>=$B9),0),0)) & " - " & INDEX(TRANSAKSI_LOG!$H$2:$H$998,MATCH(1,INDEX((TRANSAKSI_LOG!$C$2:$C$998=$C$5)*(TRANSAKSI_LOG!$J$2:$J$998=C$7)*(TRANSAKSI_LOG!$E$2:$E$998<=$B9)*(TRANSAKSI_LOG!$F$2:$F$998>=$B9),0),0)),"")} | D9: {=IFERROR(INDEX(TRANSAKSI_LOG!$M$2:$M$998,MATCH(1,INDEX((TRANSAKSI_LOG!$C$2:$C$998=$C$5)*(TRANSAKSI_LOG!$J$2:$J$998=D$7)*(TRANSAKSI_LOG!$E$2:$E$998<=$B9)*(TRANSAKSI_LOG!$F$2:$F$998>=$B9),0),0)) & " - " & INDEX(TRANSAKSI_LOG!$H$2:$H$998,MATCH(1,INDEX((TRANSAKSI_LOG!$C$2:$C$998=$C$5)*(TRANSAKSI_LOG!$J$2:$J$998=D$7)*(TRANSAKSI_LOG!$E$2:$E$998<=$B9)*(TRANSAKSI_LOG!$F$2:$F$998>=$B9),0),0)),"")} | E9: {=IFERROR(INDEX(TRANSAKSI_LOG!$M$2:$M$998,MATCH(1,INDEX((TRANSAKSI_LOG!$C$2:$C$998=$C$5)*(TRANSAKSI_LOG!$J$2:$J$998=E$7)*(TRANSAKSI_LOG!$E$2:$E$998<=$B9)*(TRANSAKSI_LOG!$F$2:$F$998>=$B9),0),0)) & " - " & INDEX(TRANSAKSI_LOG!$H$2:$H$998,MATCH(1,INDEX((TRANSAKSI_LOG!$C$2:$C$998=$C$5)*(TRANSAKSI_LOG!$J$2:$J$998=E$7)*(TRANSAKSI_LOG!$E$2:$E$998<=$B9)*(TRANSAKSI_LOG!$F$2:$F$998>=$B9),0),0)),"")} | F9: {=IFERROR(INDEX(TRANSAKSI_LOG!$M$2:$M$998,MATCH(1,INDEX((TRANSAKSI_LOG!$C$2:$C$998=$C$5)*(TRANSAKSI_LOG!$J$2:$J$998=F$7)*(TRANSAKSI_LOG!$E$2:$E$998<=$B9)*(TRANSAKSI_LOG!$F$2:$F$998>=$B9),0),0)) & " - " & INDEX(TRANSAKSI_LOG!$H$2:$H$998,MATCH(1,INDEX((TRANSAKSI_LOG!$C$2:$C$998=$C$5)*(TRANSAKSI_LOG!$J$2:$J$998=F$7)*(TRANSAKSI_LOG!$E$2:$E$998<=$B9)*(TRANSAKSI_LOG!$F$2:$F$998>=$B9),0),0)),"")} | G9: {=IFERROR(INDEX(TRANSAKSI_LOG!$M$2:$M$998,MATCH(1,INDEX((TRANSAKSI_LOG!$C$2:$C$998=$C$5)*(TRANSAKSI_LOG!$J$2:$J$998=G$7)*(TRANSAKSI_LOG!$E$2:$E$998<=$B9)*(TRANSAKSI_LOG!$F$2:$F$998>=$B9),0),0)) & " - " & INDEX(TRANSAKSI_LOG!$H$2:$H$998,MATCH(1,INDEX((TRANSAKSI_LOG!$C$2:$C$998=$C$5)*(TRANSAKSI_LOG!$J$2:$J$998=G$7)*(TRANSAKSI_LOG!$E$2:$E$998<=$B9)*(TRANSAKSI_LOG!$F$2:$F$998>=$B9),0),0)),"")} | H9: {=IFERROR(INDEX(TRANSAKSI_LOG!$M$2:$M$998,MATCH(1,INDEX((TRANSAKSI_LOG!$C$2:$C$998=$C$5)*(TRANSAKSI_LOG!$J$2:$J$998=H$7)*(TRANSAKSI_LOG!$E$2:$E$998<=$B9)*(TRANSAKSI_LOG!$F$2:$F$998>=$B9),0),0)) & " - " & INDEX(TRANSAKSI_LOG!$H$2:$H$998,MATCH(1,INDEX((TRANSAKSI_LOG!$C$2:$C$998=$C$5)*(TRANSAKSI_LOG!$J$2:$J$998=H$7)*(TRANSAKSI_LOG!$E$2:$E$998<=$B9)*(TRANSAKSI_LOG!$F$2:$F$998>=$B9),0),0)),"")}
B10: 0.34027778 | C10: {=IFERROR(INDEX(TRANSAKSI_LOG!$M$2:$M$998,MATCH(1,INDEX((TRANSAKSI_LOG!$C$2:$C$998=$C$5)*(TRANSAKSI_LOG!$J$2:$J$998=C$7)*(TRANSAKSI_LOG!$E$2:$E$998<=$B10)*(TRANSAKSI_LOG!$F$2:$F$998>=$B10),0),0)) & " - " & INDEX(TRANSAKSI_LOG!$H$2:$H$998,MATCH(1,INDEX((TRANSAKSI_LOG!$C$2:$C$998=$C$5)*(TRANSAKSI_LOG!$J$2:$J$998=C$7)*(TRANSAKSI_LOG!$E$2:$E$998<=$B10)*(TRANSAKSI_LOG!$F$2:$F$998>=$B10),0),0)),"")} | D10: {=IFERROR(INDEX(TRANSAKSI_LOG!$M$2:$M$998,MATCH(1,INDEX((TRANSAKSI_LOG!$C$2:$C$998=$C$5)*(TRANSAKSI_LOG!$J$2:$J$998=D$7)*(TRANSAKSI_LOG!$E$2:$E$998<=$B10)*(TRANSAKSI_LOG!$F$2:$F$998>=$B10),0),0)) & " - " & INDEX(TRANSAKSI_LOG!$H$2:$H$998,MATCH(1,INDEX((TRANSAKSI_LOG!$C$2:$C$998=$C$5)*(TRANSAKSI_LOG!$J$2:$J$998=D$7)*(TRANSAKSI_LOG!$E$2:$E$998<=$B10)*(TRANSAKSI_LOG!$F$2:$F$998>=$B10),0),0)),"")} | E10: {=IFERROR(INDEX(TRANSAKSI_LOG!$M$2:$M$998,MATCH(1,INDEX((TRANSAKSI_LOG!$C$2:$C$998=$C$5)*(TRANSAKSI_LOG!$J$2:$J$998=E$7)*(TRANSAKSI_LOG!$E$2:$E$998<=$B10)*(TRANSAKSI_LOG!$F$2:$F$998>=$B10),0),0)) & " - " & INDEX(TRANSAKSI_LOG!$H$2:$H$998,MATCH(1,INDEX((TRANSAKSI_LOG!$C$2:$C$998=$C$5)*(TRANSAKSI_LOG!$J$2:$J$998=E$7)*(TRANSAKSI_LOG!$E$2:$E$998<=$B10)*(TRANSAKSI_LOG!$F$2:$F$998>=$B10),0),0)),"")} | F10: {=IFERROR(INDEX(TRANSAKSI_LOG!$M$2:$M$998,MATCH(1,INDEX((TRANSAKSI_LOG!$C$2:$C$998=$C$5)*(TRANSAKSI_LOG!$J$2:$J$998=F$7)*(TRANSAKSI_LOG!$E$2:$E$998<=$B10)*(TRANSAKSI_LOG!$F$2:$F$998>=$B10),0),0)) & " - " & INDEX(TRANSAKSI_LOG!$H$2:$H$998,MATCH(1,INDEX((TRANSAKSI_LOG!$C$2:$C$998=$C$5)*(TRANSAKSI_LOG!$J$2:$J$998=F$7)*(TRANSAKSI_LOG!$E$2:$E$998<=$B10)*(TRANSAKSI_LOG!$F$2:$F$998>=$B10),0),0)),"")} | G10: {=IFERROR(INDEX(TRANSAKSI_LOG!$M$2:$M$998,MATCH(1,INDEX((TRANSAKSI_LOG!$C$2:$C$998=$C$5)*(TRANSAKSI_LOG!$J$2:$J$998=G$7)*(TRANSAKSI_LOG!$E$2:$E$998<=$B10)*(TRANSAKSI_LOG!$F$2:$F$998>=$B10),0),0)) & " - " & INDEX(TRANSAKSI_LOG!$H$2:$H$998,MATCH(1,INDEX((TRANSAKSI_LOG!$C$2:$C$998=$C$5)*(TRANSAKSI_LOG!$J$2:$J$998=G$7)*(TRANSAKSI_LOG!$E$2:$E$998<=$B10)*(TRANSAKSI_LOG!$F$2:$F$998>=$B10),0),0)),"")} | H10: {=IFERROR(INDEX(TRANSAKSI_LOG!$M$2:$M$998,MATCH(1,INDEX((TRANSAKSI_LOG!$C$2:$C$998=$C$5)*(TRANSAKSI_LOG!$J$2:$J$998=H$7)*(TRANSAKSI_LOG!$E$2:$E$998<=$B10)*(TRANSAKSI_LOG!$F$2:$F$998>=$B10),0),0)) & " - " & INDEX(TRANSAKSI_LOG!$H$2:$H$998,MATCH(1,INDEX((TRANSAKSI_LOG!$C$2:$C$998=$C$5)*(TRANSAKSI_LOG!$J$2:$J$998=H$7)*(TRANSAKSI_LOG!$E$2:$E$998<=$B10)*(TRANSAKSI_LOG!$F$2:$F$998>=$B10),0),0)),"")}
B11: 0.34375 | C11: {=IFERROR(INDEX(TRANSAKSI_LOG!$M$2:$M$998,MATCH(1,INDEX((TRANSAKSI_LOG!$C$2:$C$998=$C$5)*(TRANSAKSI_LOG!$J$2:$J$998=C$7)*(TRANSAKSI_LOG!$E$2:$E$998<=$B11)*(TRANSAKSI_LOG!$F$2:$F$998>=$B11),0),0)) & " - " & INDEX(TRANSAKSI_LOG!$H$2:$H$998,MATCH(1,INDEX((TRANSAKSI_LOG!$C$2:$C$998=$C$5)*(TRANSAKSI_LOG!$J$2:$J$998=C$7)*(TRANSAKSI_LOG!$E$2:$E$998<=$B11)*(TRANSAKSI_LOG!$F$2:$F$998>=$B11),0),0)),"")} | D11: {=IFERROR(INDEX(TRANSAKSI_LOG!$M$2:$M$998,MATCH(1,INDEX((TRANSAKSI_LOG!$C$2:$C$998=$C$5)*(TRANSAKSI_LOG!$J$2:$J$998=D$7)*(TRANSAKSI_LOG!$E$2:$E$998<=$B11)*(TRANSAKSI_LOG!$F$2:$F$998>=$B11),0),0)) & " - " & INDEX(TRANSAKSI_LOG!$H$2:$H$998,MATCH(1,INDEX((TRANSAKSI_LOG!$C$2:$C$998=$C$5)*(TRANSAKSI_LOG!$J$2:$J$998=D$7)*(TRANSAKSI_LOG!$E$2:$E$998<=$B11)*(TRANSAKSI_LOG!$F$2:$F$998>=$B11),0),0)),"")} | E11: {=IFERROR(INDEX(TRANSAKSI_LOG!$M$2:$M$998,MATCH(1,INDEX((TRANSAKSI_LOG!$C$2:$C$998=$C$5)*(TRANSAKSI_LOG!$J$2:$J$998=E$7)*(TRANSAKSI_LOG!$E$2:$E$998<=$B11)*(TRANSAKSI_LOG!$F$2:$F$998>=$B11),0),0)) & " - " & INDEX(TRANSAKSI_LOG!$H$2:$H$998,MATCH(1,INDEX((TRANSAKSI_LOG!$C$2:$C$998=$C$5)*(TRANSAKSI_LOG!$J$2:$J$998=E$7)*(TRANSAKSI_LOG!$E$2:$E$998<=$B11)*(TRANSAKSI_LOG!$F$2:$F$998>=$B11),0),0)),"")} | F11: {=IFERROR(INDEX(TRANSAKSI_LOG!$M$2:$M$998,MATCH(1,INDEX((TRANSAKSI_LOG!$C$2:$C$998=$C$5)*(TRANSAKSI_LOG!$J$2:$J$998=F$7)*(TRANSAKSI_LOG!$E$2:$E$998<=$B11)*(TRANSAKSI_LOG!$F$2:$F$998>=$B11),0),0)) & " - " & INDEX(TRANSAKSI_LOG!$H$2:$H$998,MATCH(1,INDEX((TRANSAKSI_LOG!$C$2:$C$998=$C$5)*(TRANSAKSI_LOG!$J$2:$J$998=F$7)*(TRANSAKSI_LOG!$E$2:$E$998<=$B11)*(TRANSAKSI_LOG!$F$2:$F$998>=$B11),0),0)),"")} | G11: {=IFERROR(INDEX(TRANSAKSI_LOG!$M$2:$M$998,MATCH(1,INDEX((TRANSAKSI_LOG!$C$2:$C$998=$C$5)*(TRANSAKSI_LOG!$J$2:$J$998=G$7)*(TRANSAKSI_LOG!$E$2:$E$998<=$B11)*(TRANSAKSI_LOG!$F$2:$F$998>=$B11),0),0)) & " - " & INDEX(TRANSAKSI_LOG!$H$2:$H$998,MATCH(1,INDEX((TRANSAKSI_LOG!$C$2:$C$998=$C$5)*(TRANSAKSI_LOG!$J$2:$J$998=G$7)*(TRANSAKSI_LOG!$E$2:$E$998<=$B11)*(TRANSAKSI_LOG!$F$2:$F$998>=$B11),0),0)),"")} | H11: {=IFERROR(INDEX(TRANSAKSI_LOG!$M$2:$M$998,MATCH(1,INDEX((TRANSAKSI_LOG!$C$2:$C$998=$C$5)*(TRANSAKSI_LOG!$J$2:$J$998=H$7)*(TRANSAKSI_LOG!$E$2:$E$998<=$B11)*(TRANSAKSI_LOG!$F$2:$F$998>=$B11),0),0)) & " - " & INDEX(TRANSAKSI_LOG!$H$2:$H$998,MATCH(1,INDEX((TRANSAKSI_LOG!$C$2:$C$998=$C$5)*(TRANSAKSI_LOG!$J$2:$J$998=H$7)*(TRANSAKSI_LOG!$E$2:$E$998<=$B11)*(TRANSAKSI_LOG!$F$2:$F$998>=$B11),0),0)),"")}
B12: 0.34722222 | C12: {=IFERROR(INDEX(TRANSAKSI_LOG!$M$2:$M$998,MATCH(1,INDEX((TRANSAKSI_LOG!$C$2:$C$998=$C$5)*(TRANSAKSI_LOG!$J$2:$J$998=C$7)*(TRANSAKSI_LOG!$E$2:$E$998<=$B12)*(TRANSAKSI_LOG!$F$2:$F$998>=$B12),0),0)) & " - " & INDEX(TRANSAKSI_LOG!$H$2:$H$998,MATCH(1,INDEX((TRANSAKSI_LOG!$C$2:$C$998=$C$5)*(TRANSAKSI_LOG!$J$2:$J$998=C$7)*(TRANSAKSI_LOG!$E$2:$E$998<=$B12)*(TRANSAKSI_LOG!$F$2:$F$998>=$B12),0),0)),"")} | D12: {=IFERROR(INDEX(TRANSAKSI_LOG!$M$2:$M$998,MATCH(1,INDEX((TRANSAKSI_LOG!$C$2:$C$998=$C$5)*(TRANSAKSI_LOG!$J$2:$J$998=D$7)*(TRANSAKSI_LOG!$E$2:$E$998<=$B12)*(TRANSAKSI_LOG!$F$2:$F$998>=$B12),0),0)) & " - " & INDEX(TRANSAKSI_LOG!$H$2:$H$998,MATCH(1,INDEX((TRANSAKSI_LOG!$C$2:$C$998=$C$5)*(TRANSAKSI_LOG!$J$2:$J$998=D$7)*(TRANSAKSI_LOG!$E$2:$E$998<=$B12)*(TRANSAKSI_LOG!$F$2:$F$998>=$B12),0),0)),"")} | E12: {=IFERROR(INDEX(TRANSAKSI_LOG!$M$2:$M$998,MATCH(1,INDEX((TRANSAKSI_LOG!$C$2:$C$998=$C$5)*(TRANSAKSI_LOG!$J$2:$J$998=E$7)*(TRANSAKSI_LOG!$E$2:$E$998<=$B12)*(TRANSAKSI_LOG!$F$2:$F$998>=$B12),0),0)) & " - " & INDEX(TRANSAKSI_LOG!$H$2:$H$998,MATCH(1,INDEX((TRANSAKSI_LOG!$C$2:$C$998=$C$5)*(TRANSAKSI_LOG!$J$2:$J$998=E$7)*(TRANSAKSI_LOG!$E$2:$E$998<=$B12)*(TRANSAKSI_LOG!$F$2:$F$998>=$B12),0),0)),"")} | F12: {=IFERROR(INDEX(TRANSAKSI_LOG!$M$2:$M$998,MATCH(1,INDEX((TRANSAKSI_LOG!$C$2:$C$998=$C$5)*(TRANSAKSI_LOG!$J$2:$J$998=F$7)*(TRANSAKSI_LOG!$E$2:$E$998<=$B12)*(TRANSAKSI_LOG!$F$2:$F$998>=$B12),0),0)) & " - " & INDEX(TRANSAKSI_LOG!$H$2:$H$998,MATCH(1,INDEX((TRANSAKSI_LOG!$C$2:$C$998=$C$5)*(TRANSAKSI_LOG!$J$2:$J$998=F$7)*(TRANSAKSI_LOG!$E$2:$E$998<=$B12)*(TRANSAKSI_LOG!$F$2:$F$998>=$B12),0),0)),"")} | G12: {=IFERROR(INDEX(TRANSAKSI_LOG!$M$2:$M$998,MATCH(1,INDEX((TRANSAKSI_LOG!$C$2:$C$998=$C$5)*(TRANSAKSI_LOG!$J$2:$J$998=G$7)*(TRANSAKSI_LOG!$E$2:$E$998<=$B12)*(TRANSAKSI_LOG!$F$2:$F$998>=$B12),0),0)) & " - " & INDEX(TRANSAKSI_LOG!$H$2:$H$998,MATCH(1,INDEX((TRANSAKSI_LOG!$C$2:$C$998=$C$5)*(TRANSAKSI_LOG!$J$2:$J$998=G$7)*(TRANSAKSI_LOG!$E$2:$E$998<=$B12)*(TRANSAKSI_LOG!$F$2:$F$998>=$B12),0),0)),"")} | H12: {=IFERROR(INDEX(TRANSAKSI_LOG!$M$2:$M$998,MATCH(1,INDEX((TRANSAKSI_LOG!$C$2:$C$998=$C$5)*(TRANSAKSI_LOG!$J$2:$J$998=H$7)*(TRANSAKSI_LOG!$E$2:$E$998<=$B12)*(TRANSAKSI_LOG!$F$2:$F$998>=$B12),0),0)) & " - " & INDEX(TRANSAKSI_LOG!$H$2:$H$998,MATCH(1,INDEX((TRANSAKSI_LOG!$C$2:$C$998=$C$5)*(TRANSAKSI_LOG!$J$2:$J$998=H$7)*(TRANSAKSI_LOG!$E$2:$E$998<=$B12)*(TRANSAKSI_LOG!$F$2:$F$998>=$B12),0),0)),"")}
B13: 0.35069444 | C13: {=IFERROR(INDEX(TRANSAKSI_LOG!$M$2:$M$998,MATCH(1,INDEX((TRANSAKSI_LOG!$C$2:$C$998=$C$5)*(TRANSAKSI_LOG!$J$2:$J$998=C$7)*(TRANSAKSI_LOG!$E$2:$E$998<=$B13)*(TRANSAKSI_LOG!$F$2:$F$998>=$B13),0),0)) & " - " & INDEX(TRANSAKSI_LOG!$H$2:$H$998,MATCH(1,INDEX((TRANSAKSI_LOG!$C$2:$C$998=$C$5)*(TRANSAKSI_LOG!$J$2:$J$998=C$7)*(TRANSAKSI_LOG!$E$2:$E$998<=$B13)*(TRANSAKSI_LOG!$F$2:$F$998>=$B13),0),0)),"")} | D13: {=IFERROR(INDEX(TRANSAKSI_LOG!$M$2:$M$998,MATCH(1,INDEX((TRANSAKSI_LOG!$C$2:$C$998=$C$5)*(TRANSAKSI_LOG!$J$2:$J$998=D$7)*(TRANSAKSI_LOG!$E$2:$E$998<=$B13)*(TRANSAKSI_LOG!$F$2:$F$998>=$B13),0),0)) & " - " & INDEX(TRANSAKSI_LOG!$H$2:$H$998,MATCH(1,INDEX((TRANSAKSI_LOG!$C$2:$C$998=$C$5)*(TRANSAKSI_LOG!$J$2:$J$998=D$7)*(TRANSAKSI_LOG!$E$2:$E$998<=$B13)*(TRANSAKSI_LOG!$F$2:$F$998>=$B13),0),0)),"")} | E13: {=IFERROR(INDEX(TRANSAKSI_LOG!$M$2:$M$998,MATCH(1,INDEX((TRANSAKSI_LOG!$C$2:$C$998=$C$5)*(TRANSAKSI_LOG!$J$2:$J$998=E$7)*(TRANSAKSI_LOG!$E$2:$E$998<=$B13)*(TRANSAKSI_LOG!$F$2:$F$998>=$B13),0),0)) & " - " & INDEX(TRANSAKSI_LOG!$H$2:$H$998,MATCH(1,INDEX((TRANSAKSI_LOG!$C$2:$C$998=$C$5)*(TRANSAKSI_LOG!$J$2:$J$998=E$7)*(TRANSAKSI_LOG!$E$2:$E$998<=$B13)*(TRANSAKSI_LOG!$F$2:$F$998>=$B13),0),0)),"")} | F13: {=IFERROR(INDEX(TRANSAKSI_LOG!$M$2:$M$998,MATCH(1,INDEX((TRANSAKSI_LOG!$C$2:$C$998=$C$5)*(TRANSAKSI_LOG!$J$2:$J$998=F$7)*(TRANSAKSI_LOG!$E$2:$E$998<=$B13)*(TRANSAKSI_LOG!$F$2:$F$998>=$B13),0),0)) & " - " & INDEX(TRANSAKSI_LOG!$H$2:$H$998,MATCH(1,INDEX((TRANSAKSI_LOG!$C$2:$C$998=$C$5)*(TRANSAKSI_LOG!$J$2:$J$998=F$7)*(TRANSAKSI_LOG!$E$2:$E$998<=$B13)*(TRANSAKSI_LOG!$F$2:$F$998>=$B13),0),0)),"")} | G13: {=IFERROR(INDEX(TRANSAKSI_LOG!$M$2:$M$998,MATCH(1,INDEX((TRANSAKSI_LOG!$C$2:$C$998=$C$5)*(TRANSAKSI_LOG!$J$2:$J$998=G$7)*(TRANSAKSI_LOG!$E$2:$E$998<=$B13)*(TRANSAKSI_LOG!$F$2:$F$998>=$B13),0),0)) & " - " & INDEX(TRANSAKSI_LOG!$H$2:$H$998,MATCH(1,INDEX((TRANSAKSI_LOG!$C$2:$C$998=$C$5)*(TRANSAKSI_LOG!$J$2:$J$998=G$7)*(TRANSAKSI_LOG!$E$2:$E$998<=$B13)*(TRANSAKSI_LOG!$F$2:$F$998>=$B13),0),0)),"")} | H13: {=IFERROR(INDEX(TRANSAKSI_LOG!$M$2:$M$998,MATCH(1,INDEX((TRANSAKSI_LOG!$C$2:$C$998=$C$5)*(TRANSAKSI_LOG!$J$2:$J$998=H$7)*(TRANSAKSI_LOG!$E$2:$E$998<=$B13)*(TRANSAKSI_LOG!$F$2:$F$998>=$B13),0),0)) & " - " & INDEX(TRANSAKSI_LOG!$H$2:$H$998,MATCH(1,INDEX((TRANSAKSI_LOG!$C$2:$C$998=$C$5)*(TRANSAKSI_LOG!$J$2:$J$998=H$7)*(TRANSAKSI_LOG!$E$2:$E$998<=$B13)*(TRANSAKSI_LOG!$F$2:$F$998>=$B13),0),0)),"")}
B14: 0.35416667 | C14: {=IFERROR(INDEX(TRANSAKSI_LOG!$M$2:$M$998,MATCH(1,INDEX((TRANSAKSI_LOG!$C$2:$C$998=$C$5)*(TRANSAKSI_LOG!$J$2:$J$998=C$7)*(TRANSAKSI_LOG!$E$2:$E$998<=$B14)*(TRANSAKSI_LOG!$F$2:$F$998>=$B14),0),0)) & " - " & INDEX(TRANSAKSI_LOG!$H$2:$H$998,MATCH(1,INDEX((TRANSAKSI_LOG!$C$2:$C$998=$C$5)*(TRANSAKSI_LOG!$J$2:$J$998=C$7)*(TRANSAKSI_LOG!$E$2:$E$998<=$B14)*(TRANSAKSI_LOG!$F$2:$F$998>=$B14),0),0)),"")} | D14: {=IFERROR(INDEX(TRANSAKSI_LOG!$M$2:$M$998,MATCH(1,INDEX((TRANSAKSI_LOG!$C$2:$C$998=$C$5)*(TRANSAKSI_LOG!$J$2:$J$998=D$7)*(TRANSAKSI_LOG!$E$2:$E$998<=$B14)*(TRANSAKSI_LOG!$F$2:$F$998>=$B14),0),0)) & " - " & INDEX(TRANSAKSI_LOG!$H$2:$H$998,MATCH(1,INDEX((TRANSAKSI_LOG!$C$2:$C$998=$C$5)*(TRANSAKSI_LOG!$J$2:$J$998=D$7)*(TRANSAKSI_LOG!$E$2:$E$998<=$B14)*(TRANSAKSI_LOG!$F$2:$F$998>=$B14),0),0)),"")} | E14: {=IFERROR(INDEX(TRANSAKSI_LOG!$M$2:$M$998,MATCH(1,INDEX((TRANSAKSI_LOG!$C$2:$C$998=$C$5)*(TRANSAKSI_LOG!$J$2:$J$998=E$7)*(TRANSAKSI_LOG!$E$2:$E$998<=$B14)*(TRANSAKSI_LOG!$F$2:$F$998>=$B14),0),0)) & " - " & INDEX(TRANSAKSI_LOG!$H$2:$H$998,MATCH(1,INDEX((TRANSAKSI_LOG!$C$2:$C$998=$C$5)*(TRANSAKSI_LOG!$J$2:$J$998=E$7)*(TRANSAKSI_LOG!$E$2:$E$998<=$B14)*(TRANSAKSI_LOG!$F$2:$F$998>=$B14),0),0)),"")} | F14: {=IFERROR(INDEX(TRANSAKSI_LOG!$M$2:$M$998,MATCH(1,INDEX((TRANSAKSI_LOG!$C$2:$C$998=$C$5)*(TRANSAKSI_LOG!$J$2:$J$998=F$7)*(TRANSAKSI_LOG!$E$2:$E$998<=$B14)*(TRANSAKSI_LOG!$F$2:$F$998>=$B14),0),0)) & " - " & INDEX(TRANSAKSI_LOG!$H$2:$H$998,MATCH(1,INDEX((TRANSAKSI_LOG!$C$2:$C$998=$C$5)*(TRANSAKSI_LOG!$J$2:$J$998=F$7)*(TRANSAKSI_LOG!$E$2:$E$998<=$B14)*(TRANSAKSI_LOG!$F$2:$F$998>=$B14),0),0)),"")} | G14: {=IFERROR(INDEX(TRANSAKSI_LOG!$M$2:$M$998,MATCH(1,INDEX((TRANSAKSI_LOG!$C$2:$C$998=$C$5)*(TRANSAKSI_LOG!$J$2:$J$998=G$7)*(TRANSAKSI_LOG!$E$2:$E$998<=$B14)*(TRANSAKSI_LOG!$F$2:$F$998>=$B14),0),0)) & " - " & INDEX(TRANSAKSI_LOG!$H$2:$H$998,MATCH(1,INDEX((TRANSAKSI_LOG!$C$2:$C$998=$C$5)*(TRANSAKSI_LOG!$J$2:$J$998=G$7)*(TRANSAKSI_LOG!$E$2:$E$998<=$B14)*(TRANSAKSI_LOG!$F$2:$F$998>=$B14),0),0)),"")} | H14: {=IFERROR(INDEX(TRANSAKSI_LOG!$M$2:$M$998,MATCH(1,INDEX((TRANSAKSI_LOG!$C$2:$C$998=$C$5)*(TRANSAKSI_LOG!$J$2:$J$998=H$7)*(TRANSAKSI_LOG!$E$2:$E$998<=$B14)*(TRANSAKSI_LOG!$F$2:$F$998>=$B14),0),0)) & " - " & INDEX(TRANSAKSI_LOG!$H$2:$H$998,MATCH(1,INDEX((TRANSAKSI_LOG!$C$2:$C$998=$C$5)*(TRANSAKSI_LOG!$J$2:$J$998=H$7)*(TRANSAKSI_LOG!$E$2:$E$998<=$B14)*(TRANSAKSI_LOG!$F$2:$F$998>=$B14),0),0)),"")}
B15: 0.35763889 | C15: {=IFERROR(INDEX(TRANSAKSI_LOG!$M$2:$M$998,MATCH(1,INDEX((TRANSAKSI_LOG!$C$2:$C$998=$C$5)*(TRANSAKSI_LOG!$J$2:$J$998=C$7)*(TRANSAKSI_LOG!$E$2:$E$998<=$B15)*(TRANSAKSI_LOG!$F$2:$F$998>=$B15),0),0)) & " - " & INDEX(TRANSAKSI_LOG!$H$2:$H$998,MATCH(1,INDEX((TRANSAKSI_LOG!$C$2:$C$998=$C$5)*(TRANSAKSI_LOG!$J$2:$J$998=C$7)*(TRANSAKSI_LOG!$E$2:$E$998<=$B15)*(TRANSAKSI_LOG!$F$2:$F$998>=$B15),0),0)),"")} | D15: {=IFERROR(INDEX(TRANSAKSI_LOG!$M$2:$M$998,MATCH(1,INDEX((TRANSAKSI_LOG!$C$2:$C$998=$C$5)*(TRANSAKSI_LOG!$J$2:$J$998=D$7)*(TRANSAKSI_LOG!$E$2:$E$998<=$B15)*(TRANSAKSI_LOG!$F$2:$F$998>=$B15),0),0)) & " - " & INDEX(TRANSAKSI_LOG!$H$2:$H$998,MATCH(1,INDEX((TRANSAKSI_LOG!$C$2:$C$998=$C$5)*(TRANSAKSI_LOG!$J$2:$J$998=D$7)*(TRANSAKSI_LOG!$E$2:$E$998<=$B15)*(TRANSAKSI_LOG!$F$2:$F$998>=$B15),0),0)),"")} | E15: {=IFERROR(INDEX(TRANSAKSI_LOG!$M$2:$M$998,MATCH(1,INDEX((TRANSAKSI_LOG!$C$2:$C$998=$C$5)*(TRANSAKSI_LOG!$J$2:$J$998=E$7)*(TRANSAKSI_LOG!$E$2:$E$998<=$B15)*(TRANSAKSI_LOG!$F$2:$F$998>=$B15),0),0)) & " - " & INDEX(TRANSAKSI_LOG!$H$2:$H$998,MATCH(1,INDEX((TRANSAKSI_LOG!$C$2:$C$998=$C$5)*(TRANSAKSI_LOG!$J$2:$J$998=E$7)*(TRANSAKSI_LOG!$E$2:$E$998<=$B15)*(TRANSAKSI_LOG!$F$2:$F$998>=$B15),0),0)),"")} | F15: {=IFERROR(INDEX(TRANSAKSI_LOG!$M$2:$M$998,MATCH(1,INDEX((TRANSAKSI_LOG!$C$2:$C$998=$C$5)*(TRANSAKSI_LOG!$J$2:$J$998=F$7)*(TRANSAKSI_LOG!$E$2:$E$998<=$B15)*(TRANSAKSI_LOG!$F$2:$F$998>=$B15),0),0)) & " - " & INDEX(TRANSAKSI_LOG!$H$2:$H$998,MATCH(1,INDEX((TRANSAKSI_LOG!$C$2:$C$998=$C$5)*(TRANSAKSI_LOG!$J$2:$J$998=F$7)*(TRANSAKSI_LOG!$E$2:$E$998<=$B15)*(TRANSAKSI_LOG!$F$2:$F$998>=$B15),0),0)),"")} | G15: {=IFERROR(INDEX(TRANSAKSI_LOG!$M$2:$M$998,MATCH(1,INDEX((TRANSAKSI_LOG!$C$2:$C$998=$C$5)*(TRANSAKSI_LOG!$J$2:$J$998=G$7)*(TRANSAKSI_LOG!$E$2:$E$998<=$B15)*(TRANSAKSI_LOG!$F$2:$F$998>=$B15),0),0)) & " - " & INDEX(TRANSAKSI_LOG!$H$2:$H$998,MATCH(1,INDEX((TRANSAKSI_LOG!$C$2:$C$998=$C$5)*(TRANSAKSI_LOG!$J$2:$J$998=G$7)*(TRANSAKSI_LOG!$E$2:$E$998<=$B15)*(TRANSAKSI_LOG!$F$2:$F$998>=$B15),0),0)),"")} | H15: {=IFERROR(INDEX(TRANSAKSI_LOG!$M$2:$M$998,MATCH(1,INDEX((TRANSAKSI_LOG!$C$2:$C$998=$C$5)*(TRANSAKSI_LOG!$J$2:$J$998=H$7)*(TRANSAKSI_LOG!$E$2:$E$998<=$B15)*(TRANSAKSI_LOG!$F$2:$F$998>=$B15),0),0)) & " - " & INDEX(TRANSAKSI_LOG!$H$2:$H$998,MATCH(1,INDEX((TRANSAKSI_LOG!$C$2:$C$998=$C$5)*(TRANSAKSI_LOG!$J$2:$J$998=H$7)*(TRANSAKSI_LOG!$E$2:$E$998<=$B15)*(TRANSAKSI_LOG!$F$2:$F$998>=$B15),0),0)),"")}
B16: 0.36111111 | C16: {=IFERROR(INDEX(TRANSAKSI_LOG!$M$2:$M$998,MATCH(1,INDEX((TRANSAKSI_LOG!$C$2:$C$998=$C$5)*(TRANSAKSI_LOG!$J$2:$J$998=C$7)*(TRANSAKSI_LOG!$E$2:$E$998<=$B16)*(TRANSAKSI_LOG!$F$2:$F$998>=$B16),0),0)) & " - " & INDEX(TRANSAKSI_LOG!$H$2:$H$998,MATCH(1,INDEX((TRANSAKSI_LOG!$C$2:$C$998=$C$5)*(TRANSAKSI_LOG!$J$2:$J$998=C$7)*(TRANSAKSI_LOG!$E$2:$E$998<=$B16)*(TRANSAKSI_LOG!$F$2:$F$998>=$B16),0),0)),"")} | D16: {=IFERROR(INDEX(TRANSAKSI_LOG!$M$2:$M$998,MATCH(1,INDEX((TRANSAKSI_LOG!$C$2:$C$998=$C$5)*(TRANSAKSI_LOG!$J$2:$J$998=D$7)*(TRANSAKSI_LOG!$E$2:$E$998<=$B16)*(TRANSAKSI_LOG!$F$2:$F$998>=$B16),0),0)) & " - " & INDEX(TRANSAKSI_LOG!$H$2:$H$998,MATCH(1,INDEX((TRANSAKSI_LOG!$C$2:$C$998=$C$5)*(TRANSAKSI_LOG!$J$2:$J$998=D$7)*(TRANSAKSI_LOG!$E$2:$E$998<=$B16)*(TRANSAKSI_LOG!$F$2:$F$998>=$B16),0),0)),"")} | E16: {=IFERROR(INDEX(TRANSAKSI_LOG!$M$2:$M$998,MATCH(1,INDEX((TRANSAKSI_LOG!$C$2:$C$998=$C$5)*(TRANSAKSI_LOG!$J$2:$J$998=E$7)*(TRANSAKSI_LOG!$E$2:$E$998<=$B16)*(TRANSAKSI_LOG!$F$2:$F$998>=$B16),0),0)) & " - " & INDEX(TRANSAKSI_LOG!$H$2:$H$998,MATCH(1,INDEX((TRANSAKSI_LOG!$C$2:$C$998=$C$5)*(TRANSAKSI_LOG!$J$2:$J$998=E$7)*(TRANSAKSI_LOG!$E$2:$E$998<=$B16)*(TRANSAKSI_LOG!$F$2:$F$998>=$B16),0),0)),"")} | F16: {=IFERROR(INDEX(TRANSAKSI_LOG!$M$2:$M$998,MATCH(1,INDEX((TRANSAKSI_LOG!$C$2:$C$998=$C$5)*(TRANSAKSI_LOG!$J$2:$J$998=F$7)*(TRANSAKSI_LOG!$E$2:$E$998<=$B16)*(TRANSAKSI_LOG!$F$2:$F$998>=$B16),0),0)) & " - " & INDEX(TRANSAKSI_LOG!$H$2:$H$998,MATCH(1,INDEX((TRANSAKSI_LOG!$C$2:$C$998=$C$5)*(TRANSAKSI_LOG!$J$2:$J$998=F$7)*(TRANSAKSI_LOG!$E$2:$E$998<=$B16)*(TRANSAKSI_LOG!$F$2:$F$998>=$B16),0),0)),"")} | G16: {=IFERROR(INDEX(TRANSAKSI_LOG!$M$2:$M$998,MATCH(1,INDEX((TRANSAKSI_LOG!$C$2:$C$998=$C$5)*(TRANSAKSI_LOG!$J$2:$J$998=G$7)*(TRANSAKSI_LOG!$E$2:$E$998<=$B16)*(TRANSAKSI_LOG!$F$2:$F$998>=$B16),0),0)) & " - " & INDEX(TRANSAKSI_LOG!$H$2:$H$998,MATCH(1,INDEX((TRANSAKSI_LOG!$C$2:$C$998=$C$5)*(TRANSAKSI_LOG!$J$2:$J$998=G$7)*(TRANSAKSI_LOG!$E$2:$E$998<=$B16)*(TRANSAKSI_LOG!$F$2:$F$998>=$B16),0),0)),"")} | H16: {=IFERROR(INDEX(TRANSAKSI_LOG!$M$2:$M$998,MATCH(1,INDEX((TRANSAKSI_LOG!$C$2:$C$998=$C$5)*(TRANSAKSI_LOG!$J$2:$J$998=H$7)*(TRANSAKSI_LOG!$E$2:$E$998<=$B16)*(TRANSAKSI_LOG!$F$2:$F$998>=$B16),0),0)) & " - " & INDEX(TRANSAKSI_LOG!$H$2:$H$998,MATCH(1,INDEX((TRANSAKSI_LOG!$C$2:$C$998=$C$5)*(TRANSAKSI_LOG!$J$2:$J$998=H$7)*(TRANSAKSI_LOG!$E$2:$E$998<=$B16)*(TRANSAKSI_LOG!$F$2:$F$998>=$B16),0),0)),"")}
B17: 0.36458333 | C17: {=IFERROR(INDEX(TRANSAKSI_LOG!$M$2:$M$998,MATCH(1,INDEX((TRANSAKSI_LOG!$C$2:$C$998=$C$5)*(TRANSAKSI_LOG!$J$2:$J$998=C$7)*(TRANSAKSI_LOG!$E$2:$E$998<=$B17)*(TRANSAKSI_LOG!$F$2:$F$998>=$B17),0),0)) & " - " & INDEX(TRANSAKSI_LOG!$H$2:$H$998,MATCH(1,INDEX((TRANSAKSI_LOG!$C$2:$C$998=$C$5)*(TRANSAKSI_LOG!$J$2:$J$998=C$7)*(TRANSAKSI_LOG!$E$2:$E$998<=$B17)*(TRANSAKSI_LOG!$F$2:$F$998>=$B17),0),0)),"")} | D17: {=IFERROR(INDEX(TRANSAKSI_LOG!$M$2:$M$998,MATCH(1,INDEX((TRANSAKSI_LOG!$C$2:$C$998=$C$5)*(TRANSAKSI_LOG!$J$2:$J$998=D$7)*(TRANSAKSI_LOG!$E$2:$E$998<=$B17)*(TRANSAKSI_LOG!$F$2:$F$998>=$B17),0),0)) & " - " & INDEX(TRANSAKSI_LOG!$H$2:$H$998,MATCH(1,INDEX((TRANSAKSI_LOG!$C$2:$C$998=$C$5)*(TRANSAKSI_LOG!$J$2:$J$998=D$7)*(TRANSAKSI_LOG!$E$2:$E$998<=$B17)*(TRANSAKSI_LOG!$F$2:$F$998>=$B17),0),0)),"")} | E17: {=IFERROR(INDEX(TRANSAKSI_LOG!$M$2:$M$998,MATCH(1,INDEX((TRANSAKSI_LOG!$C$2:$C$998=$C$5)*(TRANSAKSI_LOG!$J$2:$J$998=E$7)*(TRANSAKSI_LOG!$E$2:$E$998<=$B17)*(TRANSAKSI_LOG!$F$2:$F$998>=$B17),0),0)) & " - " & INDEX(TRANSAKSI_LOG!$H$2:$H$998,MATCH(1,INDEX((TRANSAKSI_LOG!$C$2:$C$998=$C$5)*(TRANSAKSI_LOG!$J$2:$J$998=E$7)*(TRANSAKSI_LOG!$E$2:$E$998<=$B17)*(TRANSAKSI_LOG!$F$2:$F$998>=$B17),0),0)),"")} | F17: {=IFERROR(INDEX(TRANSAKSI_LOG!$M$2:$M$998,MATCH(1,INDEX((TRANSAKSI_LOG!$C$2:$C$998=$C$5)*(TRANSAKSI_LOG!$J$2:$J$998=F$7)*(TRANSAKSI_LOG!$E$2:$E$998<=$B17)*(TRANSAKSI_LOG!$F$2:$F$998>=$B17),0),0)) & " - " & INDEX(TRANSAKSI_LOG!$H$2:$H$998,MATCH(1,INDEX((TRANSAKSI_LOG!$C$2:$C$998=$C$5)*(TRANSAKSI_LOG!$J$2:$J$998=F$7)*(TRANSAKSI_LOG!$E$2:$E$998<=$B17)*(TRANSAKSI_LOG!$F$2:$F$998>=$B17),0),0)),"")} | G17: {=IFERROR(INDEX(TRANSAKSI_LOG!$M$2:$M$998,MATCH(1,INDEX((TRANSAKSI_LOG!$C$2:$C$998=$C$5)*(TRANSAKSI_LOG!$J$2:$J$998=G$7)*(TRANSAKSI_LOG!$E$2:$E$998<=$B17)*(TRANSAKSI_LOG!$F$2:$F$998>=$B17),0),0)) & " - " & INDEX(TRANSAKSI_LOG!$H$2:$H$998,MATCH(1,INDEX((TRANSAKSI_LOG!$C$2:$C$998=$C$5)*(TRANSAKSI_LOG!$J$2:$J$998=G$7)*(TRANSAKSI_LOG!$E$2:$E$998<=$B17)*(TRANSAKSI_LOG!$F$2:$F$998>=$B17),0),0)),"")} | H17: {=IFERROR(INDEX(TRANSAKSI_LOG!$M$2:$M$998,MATCH(1,INDEX((TRANSAKSI_LOG!$C$2:$C$998=$C$5)*(TRANSAKSI_LOG!$J$2:$J$998=H$7)*(TRANSAKSI_LOG!$E$2:$E$998<=$B17)*(TRANSAKSI_LOG!$F$2:$F$998>=$B17),0),0)) & " - " & INDEX(TRANSAKSI_LOG!$H$2:$H$998,MATCH(1,INDEX((TRANSAKSI_LOG!$C$2:$C$998=$C$5)*(TRANSAKSI_LOG!$J$2:$J$998=H$7)*(TRANSAKSI_LOG!$E$2:$E$998<=$B17)*(TRANSAKSI_LOG!$F$2:$F$998>=$B17),0),0)),"")}
B18: 0.36805556 | C18: {=IFERROR(INDEX(TRANSAKSI_LOG!$M$2:$M$998,MATCH(1,INDEX((TRANSAKSI_LOG!$C$2:$C$998=$C$5)*(TRANSAKSI_LOG!$J$2:$J$998=C$7)*(TRANSAKSI_LOG!$E$2:$E$998<=$B18)*(TRANSAKSI_LOG!$F$2:$F$998>=$B18),0),0)) & " - " & INDEX(TRANSAKSI_LOG!$H$2:$H$998,MATCH(1,INDEX((TRANSAKSI_LOG!$C$2:$C$998=$C$5)*(TRANSAKSI_LOG!$J$2:$J$998=C$7)*(TRANSAKSI_LOG!$E$2:$E$998<=$B18)*(TRANSAKSI_LOG!$F$2:$F$998>=$B18),0),0)),"")} | D18: {=IFERROR(INDEX(TRANSAKSI_LOG!$M$2:$M$998,MATCH(1,INDEX((TRANSAKSI_LOG!$C$2:$C$998=$C$5)*(TRANSAKSI_LOG!$J$2:$J$998=D$7)*(TRANSAKSI_LOG!$E$2:$E$998<=$B18)*(TRANSAKSI_LOG!$F$2:$F$998>=$B18),0),0)) & " - " & INDEX(TRANSAKSI_LOG!$H$2:$H$998,MATCH(1,INDEX((TRANSAKSI_LOG!$C$2:$C$998=$C$5)*(TRANSAKSI_LOG!$J$2:$J$998=D$7)*(TRANSAKSI_LOG!$E$2:$E$998<=$B18)*(TRANSAKSI_LOG!$F$2:$F$998>=$B18),0),0)),"")} | E18: {=IFERROR(INDEX(TRANSAKSI_LOG!$M$2:$M$998,MATCH(1,INDEX((TRANSAKSI_LOG!$C$2:$C$998=$C$5)*(TRANSAKSI_LOG!$J$2:$J$998=E$7)*(TRANSAKSI_LOG!$E$2:$E$998<=$B18)*(TRANSAKSI_LOG!$F$2:$F$998>=$B18),0),0)) & " - " & INDEX(TRANSAKSI_LOG!$H$2:$H$998,MATCH(1,INDEX((TRANSAKSI_LOG!$C$2:$C$998=$C$5)*(TRANSAKSI_LOG!$J$2:$J$998=E$7)*(TRANSAKSI_LOG!$E$2:$E$998<=$B18)*(TRANSAKSI_LOG!$F$2:$F$998>=$B18),0),0)),"")} | F18: {=IFERROR(INDEX(TRANSAKSI_LOG!$M$2:$M$998,MATCH(1,INDEX((TRANSAKSI_LOG!$C$2:$C$998=$C$5)*(TRANSAKSI_LOG!$J$2:$J$998=F$7)*(TRANSAKSI_LOG!$E$2:$E$998<=$B18)*(TRANSAKSI_LOG!$F$2:$F$998>=$B18),0),0)) & " - " & INDEX(TRANSAKSI_LOG!$H$2:$H$998,MATCH(1,INDEX((TRANSAKSI_LOG!$C$2:$C$998=$C$5)*(TRANSAKSI_LOG!$J$2:$J$998=F$7)*(TRANSAKSI_LOG!$E$2:$E$998<=$B18)*(TRANSAKSI_LOG!$F$2:$F$998>=$B18),0),0)),"")} | G18: {=IFERROR(INDEX(TRANSAKSI_LOG!$M$2:$M$998,MATCH(1,INDEX((TRANSAKSI_LOG!$C$2:$C$998=$C$5)*(TRANSAKSI_LOG!$J$2:$J$998=G$7)*(TRANSAKSI_LOG!$E$2:$E$998<=$B18)*(TRANSAKSI_LOG!$F$2:$F$998>=$B18),0),0)) & " - " & INDEX(TRANSAKSI_LOG!$H$2:$H$998,MATCH(1,INDEX((TRANSAKSI_LOG!$C$2:$C$998=$C$5)*(TRANSAKSI_LOG!$J$2:$J$998=G$7)*(TRANSAKSI_LOG!$E$2:$E$998<=$B18)*(TRANSAKSI_LOG!$F$2:$F$998>=$B18),0),0)),"")} | H18: {=IFERROR(INDEX(TRANSAKSI_LOG!$M$2:$M$998,MATCH(1,INDEX((TRANSAKSI_LOG!$C$2:$C$998=$C$5)*(TRANSAKSI_LOG!$J$2:$J$998=H$7)*(TRANSAKSI_LOG!$E$2:$E$998<=$B18)*(TRANSAKSI_LOG!$F$2:$F$998>=$B18),0),0)) & " - " & INDEX(TRANSAKSI_LOG!$H$2:$H$998,MATCH(1,INDEX((TRANSAKSI_LOG!$C$2:$C$998=$C$5)*(TRANSAKSI_LOG!$J$2:$J$998=H$7)*(TRANSAKSI_LOG!$E$2:$E$998<=$B18)*(TRANSAKSI_LOG!$F$2:$F$998>=$B18),0),0)),"")}
B19: 0.37152778 | C19: {=IFERROR(INDEX(TRANSAKSI_LOG!$M$2:$M$998,MATCH(1,INDEX((TRANSAKSI_LOG!$C$2:$C$998=$C$5)*(TRANSAKSI_LOG!$J$2:$J$998=C$7)*(TRANSAKSI_LOG!$E$2:$E$998<=$B19)*(TRANSAKSI_LOG!$F$2:$F$998>=$B19),0),0)) & " - " & INDEX(TRANSAKSI_LOG!$H$2:$H$998,MATCH(1,INDEX((TRANSAKSI_LOG!$C$2:$C$998=$C$5)*(TRANSAKSI_LOG!$J$2:$J$998=C$7)*(TRANSAKSI_LOG!$E$2:$E$998<=$B19)*(TRANSAKSI_LOG!$F$2:$F$998>=$B19),0),0)),"")} | D19: {=IFERROR(INDEX(TRANSAKSI_LOG!$M$2:$M$998,MATCH(1,INDEX((TRANSAKSI_LOG!$C$2:$C$998=$C$5)*(TRANSAKSI_LOG!$J$2:$J$998=D$7)*(TRANSAKSI_LOG!$E$2:$E$998<=$B19)*(TRANSAKSI_LOG!$F$2:$F$998>=$B19),0),0)) & " - " & INDEX(TRANSAKSI_LOG!$H$2:$H$998,MATCH(1,INDEX((TRANSAKSI_LOG!$C$2:$C$998=$C$5)*(TRANSAKSI_LOG!$J$2:$J$998=D$7)*(TRANSAKSI_LOG!$E$2:$E$998<=$B19)*(TRANSAKSI_LOG!$F$2:$F$998>=$B19),0),0)),"")} | E19: {=IFERROR(INDEX(TRANSAKSI_LOG!$M$2:$M$998,MATCH(1,INDEX((TRANSAKSI_LOG!$C$2:$C$998=$C$5)*(TRANSAKSI_LOG!$J$2:$J$998=E$7)*(TRANSAKSI_LOG!$E$2:$E$998<=$B19)*(TRANSAKSI_LOG!$F$2:$F$998>=$B19),0),0)) & " - " & INDEX(TRANSAKSI_LOG!$H$2:$H$998,MATCH(1,INDEX((TRANSAKSI_LOG!$C$2:$C$998=$C$5)*(TRANSAKSI_LOG!$J$2:$J$998=E$7)*(TRANSAKSI_LOG!$E$2:$E$998<=$B19)*(TRANSAKSI_LOG!$F$2:$F$998>=$B19),0),0)),"")} | F19: {=IFERROR(INDEX(TRANSAKSI_LOG!$M$2:$M$998,MATCH(1,INDEX((TRANSAKSI_LOG!$C$2:$C$998=$C$5)*(TRANSAKSI_LOG!$J$2:$J$998=F$7)*(TRANSAKSI_LOG!$E$2:$E$998<=$B19)*(TRANSAKSI_LOG!$F$2:$F$998>=$B19),0),0)) & " - " & INDEX(TRANSAKSI_LOG!$H$2:$H$998,MATCH(1,INDEX((TRANSAKSI_LOG!$C$2:$C$998=$C$5)*(TRANSAKSI_LOG!$J$2:$J$998=F$7)*(TRANSAKSI_LOG!$E$2:$E$998<=$B19)*(TRANSAKSI_LOG!$F$2:$F$998>=$B19),0),0)),"")} | G19: {=IFERROR(INDEX(TRANSAKSI_LOG!$M$2:$M$998,MATCH(1,INDEX((TRANSAKSI_LOG!$C$2:$C$998=$C$5)*(TRANSAKSI_LOG!$J$2:$J$998=G$7)*(TRANSAKSI_LOG!$E$2:$E$998<=$B19)*(TRANSAKSI_LOG!$F$2:$F$998>=$B19),0),0)) & " - " & INDEX(TRANSAKSI_LOG!$H$2:$H$998,MATCH(1,INDEX((TRANSAKSI_LOG!$C$2:$C$998=$C$5)*(TRANSAKSI_LOG!$J$2:$J$998=G$7)*(TRANSAKSI_LOG!$E$2:$E$998<=$B19)*(TRANSAKSI_LOG!$F$2:$F$998>=$B19),0),0)),"")} | H19: {=IFERROR(INDEX(TRANSAKSI_LOG!$M$2:$M$998,MATCH(1,INDEX((TRANSAKSI_LOG!$C$2:$C$998=$C$5)*(TRANSAKSI_LOG!$J$2:$J$998=H$7)*(TRANSAKSI_LOG!$E$2:$E$998<=$B19)*(TRANSAKSI_LOG!$F$2:$F$998>=$B19),0),0)) & " - " & INDEX(TRANSAKSI_LOG!$H$2:$H$998,MATCH(1,INDEX((TRANSAKSI_LOG!$C$2:$C$998=$C$5)*(TRANSAKSI_LOG!$J$2:$J$998=H$7)*(TRANSAKSI_LOG!$E$2:$E$998<=$B19)*(TRANSAKSI_LOG!$F$2:$F$998>=$B19),0),0)),"")}
... B152: 0.83333333 | C152: {=IFERROR(INDEX(TRANSAKSI_LOG!$M$2:$M$998,MATCH(1,INDEX((TRANSAKSI_LOG!$C$2:$C$998=$C$5)*(TRANSAKSI_LOG!$J$2:$J$998=C$7)*(TRANSAKSI_LOG!$E$2:$E$998<=$B152)*(TRANSAKSI_LOG!$F$2:$F$998>=$B152),0),0)) & " - " & INDEX(TRANSAKSI_LOG!$H$2:$H$998,MATCH(1,INDEX((TRANSAKSI_LOG!$C$2:$C$998=$C$5)*(TRANSAKSI_LOG!$J$2:$J$998=C$7)*(TRANSAKSI_LOG!$E$2:$E$998<=$B152)*(TRANSAKSI_LOG!$F$2:$F$998>=$B152),0),0)),"")} | D152: {=IFERROR(INDEX(TRANSAKSI_LOG!$M$2:$M$998,MATCH(1,INDEX((TRANSAKSI_LOG!$C$2:$C$998=$C$5)*(TRANSAKSI_LOG!$J$2:$J$998=D$7)*(TRANSAKSI_LOG!$E$2:$E$998<=$B152)*(TRANSAKSI_LOG!$F$2:$F$998>=$B152),0),0)) & " - " & INDEX(TRANSAKSI_LOG!$H$2:$H$998,MATCH(1,INDEX((TRANSAKSI_LOG!$C$2:$C$998=$C$5)*(TRANSAKSI_LOG!$J$2:$J$998=D$7)*(TRANSAKSI_LOG!$E$2:$E$998<=$B152)*(TRANSAKSI_LOG!$F$2:$F$998>=$B152),0),0)),"")} | E152: {=IFERROR(INDEX(TRANSAKSI_LOG!$M$2:$M$998,MATCH(1,INDEX((TRANSAKSI_LOG!$C$2:$C$998=$C$5)*(TRANSAKSI_LOG!$J$2:$J$998=E$7)*(TRANSAKSI_LOG!$E$2:$E$998<=$B152)*(TRANSAKSI_LOG!$F$2:$F$998>=$B152),0),0)) & " - " & INDEX(TRANSAKSI_LOG!$H$2:$H$998,MATCH(1,INDEX((TRANSAKSI_LOG!$C$2:$C$998=$C$5)*(TRANSAKSI_LOG!$J$2:$J$998=E$7)*(TRANSAKSI_LOG!$E$2:$E$998<=$B152)*(TRANSAKSI_LOG!$F$2:$F$998>=$B152),0),0)),"")} | F152: {=IFERROR(INDEX(TRANSAKSI_LOG!$M$2:$M$998,MATCH(1,INDEX((TRANSAKSI_LOG!$C$2:$C$998=$C$5)*(TRANSAKSI_LOG!$J$2:$J$998=F$7)*(TRANSAKSI_LOG!$E$2:$E$998<=$B152)*(TRANSAKSI_LOG!$F$2:$F$998>=$B152),0),0)) & " - " & INDEX(TRANSAKSI_LOG!$H$2:$H$998,MATCH(1,INDEX((TRANSAKSI_LOG!$C$2:$C$998=$C$5)*(TRANSAKSI_LOG!$J$2:$J$998=F$7)*(TRANSAKSI_LOG!$E$2:$E$998<=$B152)*(TRANSAKSI_LOG!$F$2:$F$998>=$B152),0),0)),"")} | G152: {=IFERROR(INDEX(TRANSAKSI_LOG!$M$2:$M$998,MATCH(1,INDEX((TRANSAKSI_LOG!$C$2:$C$998=$C$5)*(TRANSAKSI_LOG!$J$2:$J$998=G$7)*(TRANSAKSI_LOG!$E$2:$E$998<=$B152)*(TRANSAKSI_LOG!$F$2:$F$998>=$B152),0),0)) & " - " & INDEX(TRANSAKSI_LOG!$H$2:$H$998,MATCH(1,INDEX((TRANSAKSI_LOG!$C$2:$C$998=$C$5)*(TRANSAKSI_LOG!$J$2:$J$998=G$7)*(TRANSAKSI_LOG!$E$2:$E$998<=$B152)*(TRANSAKSI_LOG!$F$2:$F$998>=$B152),0),0)),"")} | H152: {=IFERROR(INDEX(TRANSAKSI_LOG!$M$2:$M$998,MATCH(1,INDEX((TRANSAKSI_LOG!$C$2:$C$998=$C$5)*(TRANSAKSI_LOG!$J$2:$J$998=H$7)*(TRANSAKSI_LOG!$E$2:$E$998<=$B152)*(TRANSAKSI_LOG!$F$2:$F$998>=$B152),0),0)) & " - " & INDEX(TRANSAKSI_LOG!$H$2:$H$998,MATCH(1,INDEX((TRANSAKSI_LOG!$C$2:$C$998=$C$5)*(TRANSAKSI_LOG!$J$2:$J$998=H$7)*(TRANSAKSI_LOG!$E$2:$E$998<=$B152)*(TRANSAKSI_LOG!$F$2:$F$998>=$B152),0),0)),"")}

Sheet INVOICE
B1: DASHBOARD | D1: INPUT | F1: LOG | H1: CRM | J1: HARIAN | L1: BULANAN | N1: INVOICE | P1: JADWAL | R1: LOGIN
B4: No Invoice | C4: INV-BK-20260325-001
B5: Tanggal Cetak | C5: 46105.904
B6: Nama Customer | C6: jjhhjh
B7: Nama Anak | C7: lmlm
B8: Tanggal Booking | C8: 46106
B9: Jam Booking | C9: 0.625
B10: Layanan | C10: Newborn Starter Pack With Piercing (Paket Awal Kehidupan)
B11: Terapis | C11: Caccaca
B12: Harga | C12: 150000
B13: Diskon | C13: 0
B14: Transport | C14: 0
B15: Grand Total | C15: 150000
B16: Deposit | C16: 0
B17: Sisa Bayar | C17: 150000
B18: Status Bayar | C18: Belum Bayar

Sheet CRM PELANGGAN
A1: customer_id | B1: parent_name | C1: phone | D1: address | E1: child_name | F1: child_age | G1: visit_count | H1: total_spending | I1: avg_per_visit | J1: last_visit | K1: customer_type | L1: DASHBOARD | N1: INPUT | P1: LOG | R1: CRM | T1: HARIAN | V1: BULANAN | X1: INVOICE | Z1: JADWAL | AB1: LOGIN
A2: L0001 | B2: jjhhjh | C2: 545433423 | D2: 3e3e3 | E2: lmlm | F2: 1 Bulan | G2: 1 | H2: 150000 | I2: 150000 | J2: 25-3-2026 | K2: Baru
A3: L0002 | B3: dsdsds | C3: 897666555 | D3: 3r4r4t | E3: gghhggh | F3: 25 Tahun | G3: 1 | H3: 75000 | I3: 75000 | J3: 25-3-2026 | K3: Baru | L3: Oxytocin Stimulation Massage HC (Pijat Oksitosin)
A4: L0003 | B4: aqaq | C4: 213445432 | D4: yyuu7878 | E4: cvcv | F4: 12 Bulan | G4: 1 | H4: 60000 | I4: 60000 | J4: 25-3-2026 | K4: Baru | L4: Healthy Breath Package (Paket Nafas Sehat)
A5: L0004 | B5: rtrtrt | C5: 3455676690 | D5: jjkkk889 | E5: iuiuiu | F5: 12 Bulan | G5: 1 | H5: 85000 | I5: 85000 | J5: 26-3-2026 | K5: Baru

Sheet TRANSAKSI_LOG
A1: booking_id | B1: created_at | C1: booking_date | D1: month_name | E1: start_time | F1: end_time | G1: booking_type | H1: service_name | I1: service_category | J1: therapist_name | K1: parent_name | L1: phone | M1: child_name | N1: child_age | O1: address | P1: list_price | Q1: discount_code | R1: discount_value | S1: transport_area | T1: transport_fee | U1: grand_total | V1: deposit_amount | W1: remaining_balance | X1: payment_method | Y1: payment_status | Z1: booking_status | AA1: service_done_status | AB1: notes | AC1: therapist_fee | AD1: admin_fee | AE1: record_status | AF1: month_num | AG1: year_num | AJ1: DASHBOARD | AL1: INPUT | AN1: LOG | AP1: CRM | AR1: HARIAN | AT1: BULANAN | AV1: INVOICE | AX1: JADWAL | AZ1: LOGIN
A2: BK-20260325-001 | B2: 46106.481 | C2: 25-3-2026 | D2: Maret | E2: 0.625 | F2: 0.67361111 | G2: Inhouse | H2: Newborn Starter Pack With Piercing (Paket Awal Kehidupan) | I2: BABY | J2: Caccaca | K2: jjhhjh | L2: 545433423 | M2: lmlm | N2: 1 Bulan | O2: 3e3e3 | P2: 150000 | Q2: NONE | R2: 0 | S2: NONE | T2: 0 | U2: 150000 | V2: 0 | W2: 0 | X2: Qris | Y2: Lunas | Z2: Done | AA2: DONE | AC2: 40000 | AD2: 10000 | AE2: Active | AF2: 3 | AG2: 2026
A3: BK-20260325-002 | B3: 46106.485 | C3: 25-3-2026 | D3: Maret | E3: 0.47222222 | F3: 0.49305556 | G3: Homecare | H3: Oxytocin Stimulation Massage HC (Pijat Oksitosin) | I3: HOMECARE MOM | J3: ggagaga | K3: dsdsds | L3: 897666555 | M3: gghhggh | N3: 25 Tahun | O3: 3r4r4t | P3: 50000 | Q3: NONE | R3: 0 | S3: Zona Sedang | T3: 25000 | U3: 75000 | V3: 0 | W3: 0 | X3: Qris | Y3: Lunas | Z3: Done | AA3: DONE | AC3: 10000 | AD3: 5000 | AE3: Active | AF3: 3 | AG3: 2026
A4: BK-20260325-003 | B4: 46106.486 | C4: 25-3-2026 | D4: Maret | E4: 0.54861111 | F4: 0.56944444 | G4: Inhouse | H4: Healthy Breath Package (Paket Nafas Sehat) | I4: BABY | J4: bababab | K4: aqaq | L4: 213445432 | M4: cvcv | N4: 12 Bulan | O4: yyuu7878 | P4: 60000 | Q4: NONE | R4: 0 | S4: NONE | T4: 0 | U4: 60000 | V4: 0 | W4: 0 | X4: Qris | Y4: Lunas | Z4: Done | AA4: DONE | AC4: 10000 | AD4: 5000 | AE4: Active | AF4: 3 | AG4: 2026
A5: BK-20260326-004 | B5: 46108.364 | C5: 26-3-2026 | D5: Maret | E5: 0.375 | F5: 0.41666667 | G5: Inhouse | H5: Colic Relief Massage Baby (Pijat Kolik) | I5: BABY | J5: hahaha | K5: rtrtrt | L5: 3455676690 | M5: iuiuiu | N5: 12 Bulan | O5: jjkkk889 | P5: 85000 | Q5: NONE | R5: 0 | S5: NONE | T5: 0 | U5: 85000 | V5: 0 | W5: 0 | X5: Qris | Y5: Lunas | Z5: Done | AA5: DONE | AC5: 20000 | AD5: 10000 | AE5: Active | AF5: 3 | AG5: 2026

Sheet USER ACCESS
A1: email | B1: pin | C1: role | D1: display_name | E1: is_active | F1: notes
A2: puguh.legowo.k@gmail.com | B2: 1234 | C2: OWNER | D2: Owner Utama | E2: Y | F2: Ganti PIN setelah setup
A3: refinna.sari.86@gmail.com | B3: 4321 | C3: ADMIN | D3: Admin Frontdesk | E3: Y

Sheet STATUS MAP
A1: domain | B1: status_code | C1: label_id | D1: meaning | E1: owner_metric
A2: booking_status | B2: Active | C2: Active | D2: Booking aktif dan terjadwal | E2: booking_open
A3: booking_status | B3: Done | C3: Done | D3: Sesi selesai / closed by operation | E3: booking_done
A4: booking_status | B4: Cancelled | C4: Cancelled | D4: Dibatalkan | E4: booking_cancelled
A5: payment_status | B5: Belum Bayar | C5: Belum Bayar | D5: Belum ada pembayaran masuk | E5: ar_open
A6: payment_status | B6: DP | C6: DP | D6: Deposit masuk tetapi belum lunas | E6: ar_partial
A7: payment_status | B7: Lunas | C7: Lunas | D7: Tagihan selesai | E7: cash_closed
A8: service_done_status | B8: PENDING | C8: Pending | D8: Sesi belum dilaksanakan | E8: session_open
A9: service_done_status | B9: ONGOING | C9: On Going | D9: Sesi sedang berjalan | E9: session_live
A10: service_done_status | B10: DONE | C10: Done | D10: Sesi sudah selesai | E10: session_closed
A11: record_status | B11: Active | C11: Active | D11: Baris transaksi aktif | E11: included
A12: record_status | B12: Archived | C12: Archived | D12: Baris disimpan / tidak aktif | E12: excluded

Sheet REKAP HARIAN
A1: REKAP HARIAN | J1: DASHBOARD | L1: INPUT | N1: LOG | P1: CRM | R1: HARIAN | T1: BULANAN | V1: INVOICE | X1: JADWAL | Z1: LOGIN
B2: PILIH BULAN : | C2: PILIH TAHUN
B3: 3 | C3: 2026
A4: date | B4: total_booking | C4: homecare_count | D4: inhouse_count | E4: gross_revenue | F4: pending_payment | G4: done_count | H4: last_updated
A5: 1-3-2026 | B5: 0 | C5: 0 | D5: 0 | E5: 0 | F5: 0 | G5: 0 | H5: 27/03/2026 08:47
A6: 2-3-2026 | B6: 0 | C6: 0 | D6: 0 | E6: 0 | F6: 0 | G6: 0 | H6: 27/03/2026 08:47
A7: 3-3-2026 | B7: 0 | C7: 0 | D7: 0 | E7: 0 | F7: 0 | G7: 0 | H7: 27/03/2026 08:47
A8: 4-3-2026 | B8: 0 | C8: 0 | D8: 0 | E8: 0 | F8: 0 | G8: 0 | H8: 27/03/2026 08:47
A9: 5-3-2026 | B9: 0 | C9: 0 | D9: 0 | E9: 0 | F9: 0 | G9: 0 | H9: 27/03/2026 08:47
A10: 6-3-2026 | B10: 0 | C10: 0 | D10: 0 | E10: 0 | F10: 0 | G10: 0 | H10: 27/03/2026 08:47
A11: 7-3-2026 | B11: 0 | C11: 0 | D11: 0 | E11: 0 | F11: 0 | G11: 0 | H11: 27/03/2026 08:47
A12: 8-3-2026 | B12: 0 | C12: 0 | D12: 0 | E12: 0 | F12: 0 | G12: 0 | H12: 27/03/2026 08:47
A13: 9-3-2026 | B13: 0 | C13: 0 | D13: 0 | E13: 0 | F13: 0 | G13: 0 | H13: 27/03/2026 08:47
A14: 10-3-2026 | B14: 0 | C14: 0 | D14: 0 | E14: 0 | F14: 0 | G14: 0 | H14: 27/03/2026 08:47
A15: 11-3-2026 | B15: 0 | C15: 0 | D15: 0 | E15: 0 | F15: 0 | G15: 0 | H15: 27/03/2026 08:47
A16: 12-3-2026 | B16: 0 | C16: 0 | D16: 0 | E16: 0 | F16: 0 | G16: 0 | H16: 27/03/2026 08:47
... A35: 31-3-2026 | B35: 0 | C35: 0 | D35: 0 | E35: 0 | F35: 0 | G35: 0 | H35: 27/03/2026 08:47

Sheet REKAP BULANAN
A1: REKAP BULANAN | Q1: DASHBOARD | S1: INPUT | U1: LOG | W1: CRM | Y1: HARIAN | AA1: BULANAN | AC1: INVOICE | AE1: JADWAL | AG1: LOGIN
B2: PILIH TAHUN
B3: 2026
A4: month_name | B4: year_num | C4: total_booking | D4: homecare_count | E4: inhouse_count | F4: gross_revenue | G4: pending_payment | H4: done_count | I4: avg_ticket | J4: top_therapist | K4: top_therapist_qty | L4: total_service | M4: top_service | N4: top_service_qty | O4: last_updated
A5: Januari | B5: 2026 | C5: 0 | D5: 0 | E5: 0 | F5: 0 | G5: 0 | H5: 0 | I5: 0 | K5: 0 | L5: 0 | N5: 0 | O5: 27/03/2026 08:47
A6: Februari | B6: 2026 | C6: 0 | D6: 0 | E6: 0 | F6: 0 | G6: 0 | H6: 0 | I6: 0 | K6: 0 | L6: 0 | N6: 0 | O6: 27/03/2026 08:47
A7: Maret | B7: 2026 | C7: 4 | D7: 1 | E7: 3 | F7: 370000 | G7: 0 | H7: 4 | I7: 92500 | J7: bababab | K7: 1 | L7: 4 | M7: Colic Relief Massage Baby (Pijat Kolik) | N7: 1 | O7: 27/03/2026 08:47
A8: April | B8: 2026 | C8: 0 | D8: 0 | E8: 0 | F8: 0 | G8: 0 | H8: 0 | I8: 0 | K8: 0 | L8: 0 | N8: 0 | O8: 27/03/2026 08:47
A9: Mei | B9: 2026 | C9: 0 | D9: 0 | E9: 0 | F9: 0 | G9: 0 | H9: 0 | I9: 0 | K9: 0 | L9: 0 | N9: 0 | O9: 27/03/2026 08:47
A10: Juni | B10: 2026 | C10: 0 | D10: 0 | E10: 0 | F10: 0 | G10: 0 | H10: 0 | I10: 0 | K10: 0 | L10: 0 | N10: 0 | O10: 27/03/2026 08:47
A11: Juli | B11: 2026 | C11: 0 | D11: 0 | E11: 0 | F11: 0 | G11: 0 | H11: 0 | I11: 0 | K11: 0 | L11: 0 | N11: 0 | O11: 27/03/2026 08:47
A12: Agustus | B12: 2026 | C12: 0 | D12: 0 | E12: 0 | F12: 0 | G12: 0 | H12: 0 | I12: 0 | K12: 0 | L12: 0 | N12: 0 | O12: 27/03/2026 08:47
A13: September | B13: 2026 | C13: 0 | D13: 0 | E13: 0 | F13: 0 | G13: 0 | H13: 0 | I13: 0 | K13: 0 | L13: 0 | N13: 0 | O13: 27/03/2026 08:47
A14: Oktober | B14: 2026 | C14: 0 | D14: 0 | E14: 0 | F14: 0 | G14: 0 | H14: 0 | I14: 0 | K14: 0 | L14: 0 | N14: 0 | O14: 27/03/2026 08:47
A15: November | B15: 2026 | C15: 0 | D15: 0 | E15: 0 | F15: 0 | G15: 0 | H15: 0 | I15: 0 | K15: 0 | L15: 0 | N15: 0 | O15: 27/03/2026 08:47
A16: Desember | B16: 2026 | C16: 0 | D16: 0 | E16: 0 | F16: 0 | G16: 0 | H16: 0 | I16: 0 | K16: 0 | L16: 0 | N16: 0 | O16: 27/03/2026 08:47

Sheet KOMISI TERAPIS
A1: KOMISI TERAPIS
A2: PILIH BULAN : | B2: PILIH TAHUN
A3: 3 | B3: 2026
A4: therapist_code | B4: therapist_name | C4: total_booking | D4: service_fee_total | E4: transport_fee_total | F4: grand_incentive | G4: last_updated
A5: T001 | B5: bababab | C5: =IFNA(COUNTIFS(TRANSAKSI_LOG!J:J,B5,TRANSAKSI_LOG!Y:Y,"lunas",TRANSAKSI_LOG!AA:AA,"Done",TRANSAKSI_LOG!AF:AF,$A$3,TRANSAKSI_LOG!AG:AG,$B$3),0) -> 1 | D5: =IFNA(SUMIFS(TRANSAKSI_LOG!AC:AC,TRANSAKSI_LOG!J:J,B5,TRANSAKSI_LOG!Y:Y,"lunas",TRANSAKSI_LOG!AA:AA,"Done",TRANSAKSI_LOG!AF:AF,$A$3,TRANSAKSI_LOG!AG:AG,$B$3),0) -> 10000 | E5: =IFNA(SUMIFS(TRANSAKSI_LOG!T:T,TRANSAKSI_LOG!J:J,B5,TRANSAKSI_LOG!G:G,"Homecare",TRANSAKSI_LOG!Y:Y,"lunas",TRANSAKSI_LOG!AA:AA,"Done",TRANSAKSI_LOG!AF:AF,$A$3,TRANSAKSI_LOG!AG:AG,$B$3),0) -> 0 | F5: =D5+E5 -> 10000 | G5: 26/03/2026 22:36
A6: T002 | B6: Caccaca | C6: =IFNA(COUNTIFS(TRANSAKSI_LOG!J:J,B6,TRANSAKSI_LOG!Y:Y,"lunas",TRANSAKSI_LOG!AA:AA,"Done",TRANSAKSI_LOG!AF:AF,$A$3,TRANSAKSI_LOG!AG:AG,$B$3),0) -> 1 | D6: =IFNA(SUMIFS(TRANSAKSI_LOG!AC:AC,TRANSAKSI_LOG!J:J,B6,TRANSAKSI_LOG!Y:Y,"lunas",TRANSAKSI_LOG!AA:AA,"Done",TRANSAKSI_LOG!AF:AF,$A$3,TRANSAKSI_LOG!AG:AG,$B$3),0) -> 40000 | E6: =IFNA(SUMIFS(TRANSAKSI_LOG!T:T,TRANSAKSI_LOG!J:J,B6,TRANSAKSI_LOG!G:G,"Homecare",TRANSAKSI_LOG!Y:Y,"lunas",TRANSAKSI_LOG!AA:AA,"Done",TRANSAKSI_LOG!AF:AF,$A$3,TRANSAKSI_LOG!AG:AG,$B$3),0) -> 0 | F6: =D6+E6 -> 40000 | G6: 26/03/2026 22:36
A7: T003 | B7: ggagaga | C7: =IFNA(COUNTIFS(TRANSAKSI_LOG!J:J,B7,TRANSAKSI_LOG!Y:Y,"lunas",TRANSAKSI_LOG!AA:AA,"Done",TRANSAKSI_LOG!AF:AF,$A$3,TRANSAKSI_LOG!AG:AG,$B$3),0) -> 1 | D7: =IFNA(SUMIFS(TRANSAKSI_LOG!AC:AC,TRANSAKSI_LOG!J:J,B7,TRANSAKSI_LOG!Y:Y,"lunas",TRANSAKSI_LOG!AA:AA,"Done",TRANSAKSI_LOG!AF:AF,$A$3,TRANSAKSI_LOG!AG:AG,$B$3),0) -> 10000 | E7: =IFNA(SUMIFS(TRANSAKSI_LOG!T:T,TRANSAKSI_LOG!J:J,B7,TRANSAKSI_LOG!G:G,"Homecare",TRANSAKSI_LOG!Y:Y,"lunas",TRANSAKSI_LOG!AA:AA,"Done",TRANSAKSI_LOG!AF:AF,$A$3,TRANSAKSI_LOG!AG:AG,$B$3),0) -> 25000 | F7: =D7+E7 -> 35000 | G7: 46107.942
A8: T004 | B8: hahaha | C8: =IFNA(COUNTIFS(TRANSAKSI_LOG!J:J,B8,TRANSAKSI_LOG!Y:Y,"lunas",TRANSAKSI_LOG!AA:AA,"Done",TRANSAKSI_LOG!AF:AF,$A$3,TRANSAKSI_LOG!AG:AG,$B$3),0) -> 1 | D8: =IFNA(SUMIFS(TRANSAKSI_LOG!AC:AC,TRANSAKSI_LOG!J:J,B8,TRANSAKSI_LOG!Y:Y,"lunas",TRANSAKSI_LOG!AA:AA,"Done",TRANSAKSI_LOG!AF:AF,$A$3,TRANSAKSI_LOG!AG:AG,$B$3),0) -> 20000 | E8: =IFNA(SUMIFS(TRANSAKSI_LOG!T:T,TRANSAKSI_LOG!J:J,B8,TRANSAKSI_LOG!G:G,"Homecare",TRANSAKSI_LOG!Y:Y,"lunas",TRANSAKSI_LOG!AA:AA,"Done",TRANSAKSI_LOG!AF:AF,$A$3,TRANSAKSI_LOG!AG:AG,$B$3),0) -> 0 | F8: =D8+E8 -> 20000 | G8: 46107.942

Sheet KOMISI SA
A1: KOMISI TERAPIS
A2: PILIH BULAN : | B2: PILIH TAHUN
A3: 3 | B3: 2026
A4: SA_code | B4: SA_name | C4: total_booking | D4: service_fee_total | E4: transport_fee_total | F4: grand_incentive | G4: last_updated
A5: S001 | B5: fhfhfhf | C5: =IFNA(COUNTIFS(TRANSAKSI_LOG!AE:AE,"Active",TRANSAKSI_LOG!Y:Y,"lunas",TRANSAKSI_LOG!AA:AA,"Done",TRANSAKSI_LOG!AF:AF,$A$3,TRANSAKSI_LOG!AG:AG,$B$3),0) -> 4 | D5: =IFNA(SUMIFS(TRANSAKSI_LOG!AD:AD,TRANSAKSI_LOG!AE:AE,"Active",TRANSAKSI_LOG!Y:Y,"lunas",TRANSAKSI_LOG!AA:AA,"Done",TRANSAKSI_LOG!AF:AF,$A$3,TRANSAKSI_LOG!AG:AG,$B$3),0) -> 30000 | E5: =0 -> 0 | F5: =D5+E5 -> 30000 | G5: 25/03/2026 11:32

Sheet MASTER_LAYANAN
A1: service_code | B1: service_name | C1: service_category | D1: duration_min | E1: price | F1: therapist_fee | G1: admin_fee | H1: active | I1: notes
A2: B001 | B2: BABY | C2: Baby Relaxation Massage (Pijat Relaksasi Bayi) | D2: 45 | E2: 75000 | F2: 20 | G2: 5 | H2: YA | L2: =IFERROR(__xludf.DUMMYFUNCTION("FILTER(MASTER_LAYANAN!C2:C1000, MASTER_LAYANAN!H2:H1000 = ""Ya"")"),"Baby Relaxation Massage (Pijat Relaksasi Bayi)") -> Baby Relaxation Massage (Pijat Relaksasi Bayi)
A3: B002 | B3: BABY | C3: Warm Water Swim Therapy (Renang & Terapi Air Hangat) | D3: 15 | E3: 50000 | F3: 10 | G3: 5 | H3: YA | L3: =IFERROR(__xludf.DUMMYFUNCTION("""COMPUTED_VALUE"""),"Warm Water Swim Therapy (Renang & Terapi Air Hangat)") -> Warm Water Swim Therapy (Renang & Terapi Air Hangat)
A4: B003 | B4: BABY | C4: Basic Baby Gym (Gym Bayi Dasar) | D4: 5 | E4: 20000 | F4: 5 | G4: 2 | H4: YA | L4: =IFERROR(__xludf.DUMMYFUNCTION("""COMPUTED_VALUE"""),"Basic Baby Gym (Gym Bayi Dasar)") -> Basic Baby Gym (Gym Bayi Dasar)
A5: B004 | B5: BABY | C5: Baby Ball Gym (Gym Bola Bayi) | D5: 5 | E5: 20000 | F5: 5 | G5: 2 | H5: YA | L5: =IFERROR(__xludf.DUMMYFUNCTION("""COMPUTED_VALUE"""),"Baby Ball Gym (Gym Bola Bayi)") -> Baby Ball Gym (Gym Bola Bayi)
A6: B005 | B6: BABY | C6: Baby Sensory Bubble Bath (Mandi Busa Sensorik Bayi) | D6: 15 | E6: 50000 | F6: 10 | G6: 5 | H6: YA | L6: =IFERROR(__xludf.DUMMYFUNCTION("""COMPUTED_VALUE"""),"Baby Sensory Bubble Bath (Mandi Busa Sensorik Bayi)") -> Baby Sensory Bubble Bath (Mandi Busa Sensorik Bayi)
A7: B006 | B7: BABY | C7: Tuina Massage Baby (Pijat Tuina) | D7: 60 | E7: 85000 | F7: 20 | G7: 10 | H7: YA | L7: =IFERROR(__xludf.DUMMYFUNCTION("""COMPUTED_VALUE"""),"Tuina Massage Baby (Pijat Tuina)") -> Tuina Massage Baby (Pijat Tuina)
A8: B007 | B8: BABY | C8: Colic Relief Massage Baby (Pijat Kolik) | D8: 60 | E8: 85000 | F8: 20 | G8: 10 | H8: YA | L8: =IFERROR(__xludf.DUMMYFUNCTION("""COMPUTED_VALUE"""),"Colic Relief Massage Baby (Pijat Kolik)") -> Colic Relief Massage Baby (Pijat Kolik)
A9: B008 | B9: BABY | C9: Cough & Cold Massage Baby(Pijat Batuk & Pilek) | D9: 60 | E9: 85000 | F9: 20 | G9: 10 | H9: YA | L9: =IFERROR(__xludf.DUMMYFUNCTION("""COMPUTED_VALUE"""),"Cough & Cold Massage Baby(Pijat Batuk & Pilek)") -> Cough & Cold Massage Baby(Pijat Batuk & Pilek)
A10: B009 | B10: BABY | C10: Constipation Relief Massage Baby (Pijat Konstipasi) | D10: 60 | E10: 85000 | F10: 20 | G10: 10 | H10: YA | L10: =IFERROR(__xludf.DUMMYFUNCTION("""COMPUTED_VALUE"""),"Constipation Relief Massage Baby (Pijat Konstipasi)") -> Constipation Relief Massage Baby (Pijat Konstipasi)
A11: B010 | B11: BABY | C11: Baby Ear Piercing (Tindik Telinga Bayi) | D11: 5 | E11: 50000 | F11: 10 | G11: 5 | H11: YA | L11: =IFERROR(__xludf.DUMMYFUNCTION("""COMPUTED_VALUE"""),"Baby Ear Piercing (Tindik Telinga Bayi)") -> Baby Ear Piercing (Tindik Telinga Bayi)
A12: B011 | B12: BABY | C12: Baby Nail Trimming (Pemotongan Kuku Bayi) | D12: 5 | E12: 15000 | F12: 5 | G12: 2 | H12: YA | L12: =IFERROR(__xludf.DUMMYFUNCTION("""COMPUTED_VALUE"""),"Baby Nail Trimming (Pemotongan Kuku Bayi)") -> Baby Nail Trimming (Pemotongan Kuku Bayi)
A13: B012 | B13: BABY | C13: Newborn Head Shaving (Cukur Gundul Bayi) | D13: 15 | E13: 50000 | F13: 10 | G13: 5 | H13: YA | L13: =IFERROR(__xludf.DUMMYFUNCTION("""COMPUTED_VALUE"""),"Newborn Head Shaving (Cukur Gundul Bayi)") -> Newborn Head Shaving (Cukur Gundul Bayi)
A14: B013 | B14: BABY | C14: Basic Personal Hygiene (Perawatan Kebersihan Dasar) | D14: 15 | E14: 20000 | F14: 5 | G14: 2 | H14: YA | L14: =IFERROR(__xludf.DUMMYFUNCTION("""COMPUTED_VALUE"""),"Basic Personal Hygiene (Perawatan Kebersihan Dasar)") -> Basic Personal Hygiene (Perawatan Kebersihan Dasar)
A15: B014 | B15: BABY | C15: Baby Infrared Therapy (Terapi Infrared Bayi) | D15: 20 | E15: 50000 | F15: 10 | G15: 5 | H15: YA | L15: =IFERROR(__xludf.DUMMYFUNCTION("""COMPUTED_VALUE"""),"Baby Infrared Therapy (Terapi Infrared Bayi)") -> Baby Infrared Therapy (Terapi Infrared Bayi)
A16: B015 | B16: BABY | C16: Baby Nebulizer Therapy (Terapi Nebulizer Bayi) | D16: 10 | E16: 50000 | F16: 10 | G16: 5 | H16: YA | L16: =IFERROR(__xludf.DUMMYFUNCTION("""COMPUTED_VALUE"""),"Baby Nebulizer Therapy (Terapi Nebulizer Bayi)") -> Baby Nebulizer Therapy (Terapi Nebulizer Bayi)
A17: B016 | B17: BABY | C17: Newborn Starter Pack With Piercing (Paket Awal Kehidupan) | D17: 70 | E17: 150000 | F17: 40 | G17: 10 | H17: YA | L17: =IFERROR(__xludf.DUMMYFUNCTION("""COMPUTED_VALUE"""),"Newborn Starter Pack With Piercing (Paket Awal Kehidupan)") -> Newborn Starter Pack With Piercing (Paket Awal Kehidupan)
A18: B017 | B18: BABY | C18: Newborn Starter Pack Without Piercing (Paket Awal Kehidupan) | D18: 70 | E18: 120000 | F18: 35 | G18: 10 | H18: YA | L18: =IFERROR(__xludf.DUMMYFUNCTION("""COMPUTED_VALUE"""),"Newborn Starter Pack Without Piercing (Paket Awal Kehidupan)") -> Newborn Starter Pack Without Piercing (Paket Awal Kehidupan)
A19: B018 | B19: BABY | C19: Optimal Energy Package (Paket Energi Optimal) | D19: 60 | E19: 125000 | F19: 35 | G19: 10 | H19: YA | L19: =IFERROR(__xludf.DUMMYFUNCTION("""COMPUTED_VALUE"""),"Optimal Energy Package (Paket Energi Optimal)") -> Optimal Energy Package (Paket Energi Optimal)
A20: B019 | B20: BABY | C20: Touch of Love Package (Paket Sentuh Cinta) | D20: 60 | E20: 90000 | F20: 20 | G20: 10 | H20: YA | L20: =IFERROR(__xludf.DUMMYFUNCTION("""COMPUTED_VALUE"""),"Touch of Love Package (Paket Sentuh Cinta)") -> Touch of Love Package (Paket Sentuh Cinta)
A21: B020 | B21: BABY | C21: Clear Breath Premium (Paket Nafas Lega) | D21: 60 | E21: 145000 | F21: 35 | G21: 10 | H21: YA | L21: =IFERROR(__xludf.DUMMYFUNCTION("""COMPUTED_VALUE"""),"Clear Breath Premium (Paket Nafas Lega)") -> Clear Breath Premium (Paket Nafas Lega)
A22: B021 | B22: BABY | C22: Clear Breath Premium WITHOUT UAP (Paket Nafas Lega Tanpa Uap) | D22: 60 | E22: 125000 | F22: 35 | G22: 10 | H22: YA | L22: =IFERROR(__xludf.DUMMYFUNCTION("""COMPUTED_VALUE"""),"Clear Breath Premium WITHOUT UAP (Paket Nafas Lega Tanpa Uap)") -> Clear Breath Premium WITHOUT UAP (Paket Nafas Lega Tanpa Uap)
A23: B022 | B23: BABY | C23: Healthy Breath Package (Paket Nafas Sehat) | D23: 30 | E23: 60000 | F23: 10 | G23: 5 | H23: YA | L23: =IFERROR(__xludf.DUMMYFUNCTION("""COMPUTED_VALUE"""),"Healthy Breath Package (Paket Nafas Sehat)") -> Healthy Breath Package (Paket Nafas Sehat)
A24: B023 | B24: BABY | C24: Healthy Breath Package 2x (Paket Nafas Sehat) | D24: 30 | E24: 100000 | F24: 40 | G24: 10 | H24: YA | L24: =IFERROR(__xludf.DUMMYFUNCTION("""COMPUTED_VALUE"""),"Healthy Breath Package 2x (Paket Nafas Sehat)") -> Healthy Breath Package 2x (Paket Nafas Sehat)
A25: K001 | B25: KID | C25: Kids Massage (Pijat Anak) | D25: 45 | E25: 80000 | F25: 20 | G25: 10 | H25: YA | L25: =IFERROR(__xludf.DUMMYFUNCTION("""COMPUTED_VALUE"""),"Kids Massage (Pijat Anak)") -> Kids Massage (Pijat Anak)
A26: K002 | B26: KID | C26: Kids Body Scrub (Lulur Anak) | D26: 30 | E26: 40000 | F26: 10 | G26: 5 | H26: YA | L26: =IFERROR(__xludf.DUMMYFUNCTION("""COMPUTED_VALUE"""),"Kids Body Scrub (Lulur Anak)") -> Kids Body Scrub (Lulur Anak)
A27: K004 | B27: KID | C27: Kid Sensory Bubble Bath (Mandi Busa Sensorik Anak) | D27: 15 | E27: 40000 | F27: 10 | G27: 5 | H27: YA | L27: =IFERROR(__xludf.DUMMYFUNCTION("""COMPUTED_VALUE"""),"Kid Sensory Bubble Bath (Mandi Busa Sensorik Anak)") -> Kid Sensory Bubble Bath (Mandi Busa Sensorik Anak)
A28: K003 | B28: KID | C28: Kids Facial Mask (Masker Muka) | D28: 15 | E28: 20000 | F28: 5 | G28: 2 | H28: YA | L28: =IFERROR(__xludf.DUMMYFUNCTION("""COMPUTED_VALUE"""),"Kids Facial Mask (Masker Muka)") -> Kids Facial Mask (Masker Muka)
A29: K005 | B29: KID | C29: Tuina Massage Kid(Pijat Tuina) | D29: 60 | E29: 90000 | F29: 20 | G29: 10 | H29: YA | L29: =IFERROR(__xludf.DUMMYFUNCTION("""COMPUTED_VALUE"""),"Tuina Massage Kid(Pijat Tuina)") -> Tuina Massage Kid(Pijat Tuina)
A30: K006 | B30: KID | C30: Colic Relief Massage Kid(Pijat Kolik) | D30: 60 | E30: 90000 | F30: 20 | G30: 10 | H30: YA | L30: =IFERROR(__xludf.DUMMYFUNCTION("""COMPUTED_VALUE"""),"Colic Relief Massage Kid(Pijat Kolik)") -> Colic Relief Massage Kid(Pijat Kolik)
A31: K007 | B31: KID | C31: Cough & Cold Massage Kid(Pijat Batuk & Pilek) | D31: 60 | E31: 90000 | F31: 20 | G31: 10 | H31: YA | L31: =IFERROR(__xludf.DUMMYFUNCTION("""COMPUTED_VALUE"""),"Cough & Cold Massage Kid(Pijat Batuk & Pilek)") -> Cough & Cold Massage Kid(Pijat Batuk & Pilek)
A32: K008 | B32: KID | C32: Constipation Relief Massage Kid (Pijat Konstipasi) | D32: 60 | E32: 90000 | F32: 20 | G32: 10 | H32: YA | L32: =IFERROR(__xludf.DUMMYFUNCTION("""COMPUTED_VALUE"""),"Constipation Relief Massage Kid (Pijat Konstipasi)") -> Constipation Relief Massage Kid (Pijat Konstipasi)
A33: K009 | B33: KID | C33: Kid Ear Piercing (Tindik Telinga Anak) | D33: 5 | E33: 50000 | F33: 10 | G33: 5 | H33: YA | L33: =IFERROR(__xludf.DUMMYFUNCTION("""COMPUTED_VALUE"""),"Kid Ear Piercing (Tindik Telinga Anak)") -> Kid Ear Piercing (Tindik Telinga Anak)
A34: K010 | B34: KID | C34: Kid Nail Trimming (Pemotongan Kuku Anak) | D34: 5 | E34: 15000 | F34: 5 | G34: 2 | H34: YA | L34: =IFERROR(__xludf.DUMMYFUNCTION("""COMPUTED_VALUE"""),"Kid Nail Trimming (Pemotongan Kuku Anak)") -> Kid Nail Trimming (Pemotongan Kuku Anak)
A35: K011 | B35: KID | C35: Kid Infrared Therapy (Terapi Infrared Anak) | D35: 10 | E35: 50000 | F35: 10 | G35: 5 | H35: YA | L35: =IFERROR(__xludf.DUMMYFUNCTION("""COMPUTED_VALUE"""),"Kid Infrared Therapy (Terapi Infrared Anak)") -> Kid Infrared Therapy (Terapi Infrared Anak)
A36: K012 | B36: KID | C36: Kid Nebulizer Therapy (Terapi Nebulizer Anak) | D36: 10 | E36: 50000 | F36: 10 | G36: 5 | H36: YA | L36: =IFERROR(__xludf.DUMMYFUNCTION("""COMPUTED_VALUE"""),"Kid Nebulizer Therapy (Terapi Nebulizer Anak)") -> Kid Nebulizer Therapy (Terapi Nebulizer Anak)
A37: K013 | B37: KID | C37: Sensory Spa Package (Paket Spa Sensorik) | D37: 70 | E37: 80000 | F37: 20 | G37: 10 | H37: YA | L37: =IFERROR(__xludf.DUMMYFUNCTION("""COMPUTED_VALUE"""),"Sensory Spa Package (Paket Spa Sensorik)") -> Sensory Spa Package (Paket Spa Sensorik)
A38: K014 | B38: KID | C38: Relaxation Duo Package (Paket Duo Relaksasi) | D38: 60 | E38: 120000 | F38: 35 | G38: 10 | H38: YA | L38: =IFERROR(__xludf.DUMMYFUNCTION("""COMPUTED_VALUE"""),"Relaxation Duo Package (Paket Duo Relaksasi)") -> Relaxation Duo Package (Paket Duo Relaksasi)
A39: K015 | B39: KID | C39: Clear Air Therapy Package (Paket Terapi Udara Bersih) | D39: 90 | E39: 165000 | F39: 40 | G39: 10 | H39: YA | L39: =IFERROR(__xludf.DUMMYFUNCTION("""COMPUTED_VALUE"""),"Clear Air Therapy Package (Paket Terapi Udara Bersih)") -> Clear Air Therapy Package (Paket Terapi Udara Bersih)
A40: K016 | B40: KID | C40: Healthy Breath Package 1x ( Nafas Sehat 1x ) | D40: 30 | E40: 60000 | F40: 20 | G40: 5 | H40: YA | L40: =IFERROR(__xludf.DUMMYFUNCTION("""COMPUTED_VALUE"""),"Healthy Breath Package 1x ( Nafas Sehat 1x )") -> Healthy Breath Package 1x ( Nafas Sehat 1x )
A41: K017 | B41: KID | C41: Healthy Breath Package 2x ( Nafas Sehat 2x ) | D41: 30 | E41: 100000 | F41: 20 | G41: 10 | H41: YA | L41: =IFERROR(__xludf.DUMMYFUNCTION("""COMPUTED_VALUE"""),"Healthy Breath Package 2x ( Nafas Sehat 2x )") -> Healthy Breath Package 2x ( Nafas Sehat 2x )
A42: M001 | B42: MOM | C42: Prenatal Wellness Massage (Pijat Prenatal) | D42: 70 | E42: 150000 | F42: 40 | G42: 10 | H42: YA | L42: =IFERROR(__xludf.DUMMYFUNCTION("""COMPUTED_VALUE"""),"Prenatal Wellness Massage (Pijat Prenatal)") -> Prenatal Wellness Massage (Pijat Prenatal)
A43: M002 | B43: MOM | C43: Facial Acupressure & Mask (Totok Wajah & Masker Wajah) | D43: 20 | E43: 40000 | F43: 10 | G43: 5 | H43: YA | L43: =IFERROR(__xludf.DUMMYFUNCTION("""COMPUTED_VALUE"""),"Facial Acupressure & Mask (Totok Wajah & Masker Wajah)") -> Facial Acupressure & Mask (Totok Wajah & Masker Wajah)
A44: M003 | B44: MOM | C44: Foot Spa Therapy (Perawatan Foot Spa) | D44: 15 | E44: 40000 | F44: 10 | G44: 5 | H44: YA | L44: =IFERROR(__xludf.DUMMYFUNCTION("""COMPUTED_VALUE"""),"Foot Spa Therapy (Perawatan Foot Spa)") -> Foot Spa Therapy (Perawatan Foot Spa)
A45: M004 | B45: MOM | C45: Back & Arms Relaxation Massage (Pijat Relaksasi Punggung & Tangan) | D45: 30 | E45: 65000 | F45: 10 | G45: 5 | H45: YA | L45: =IFERROR(__xludf.DUMMYFUNCTION("""COMPUTED_VALUE"""),"Back & Arms Relaxation Massage (Pijat Relaksasi Punggung & Tangan)") -> Back & Arms Relaxation Massage (Pijat Relaksasi Punggung & Tangan)
A46: M005 | B46: MOM | C46: Early Pregnancy Revitalization Package (Perawatan Awal Kehamilan) | D46: 60 | E46: 95000 | F46: 20 | G46: 10 | H46: YA | L46: =IFERROR(__xludf.DUMMYFUNCTION("""COMPUTED_VALUE"""),"Early Pregnancy Revitalization Package (Perawatan Awal Kehamilan)") -> Early Pregnancy Revitalization Package (Perawatan Awal Kehamilan)
A47: M006 | B47: MOM | C47: Mid-Pregnancy Wellness Package (Perawatan Tengah Kehamilan) | D47: 90 | E47: 185000 | F47: 40 | G47: 10 | H47: YA | L47: =IFERROR(__xludf.DUMMYFUNCTION("""COMPUTED_VALUE"""),"Mid-Pregnancy Wellness Package (Perawatan Tengah Kehamilan)") -> Mid-Pregnancy Wellness Package (Perawatan Tengah Kehamilan)
A48: M007 | B48: MOM | C48: Postnatal Recovery Massage (Pijat Pemulihan Pascapersalinan) | D48: 70 | E48: 150000 | F48: 40 | G48: 10 | H48: YA | L48: =IFERROR(__xludf.DUMMYFUNCTION("""COMPUTED_VALUE"""),"Postnatal Recovery Massage (Pijat Pemulihan Pascapersalinan)") -> Postnatal Recovery Massage (Pijat Pemulihan Pascapersalinan)
A49: M008 | B49: MOM | C49: Platinum Recovery Package (Paket Platinum Pascapersalinan) | D49: 100 | E49: 190000 | F49: 40 | G49: 10 | H49: YA | L49: =IFERROR(__xludf.DUMMYFUNCTION("""COMPUTED_VALUE"""),"Platinum Recovery Package (Paket Platinum Pascapersalinan)") -> Platinum Recovery Package (Paket Platinum Pascapersalinan)
A50: M010 | B50: MOM | C50: Lactation Support Package (Paket Lancar ASI) | D50: 80 | E50: 90000 | F50: 20 | G50: 10 | H50: YA | L50: =IFERROR(__xludf.DUMMYFUNCTION("""COMPUTED_VALUE"""),"Lactation Support Package (Paket Lancar ASI)") -> Lactation Support Package (Paket Lancar ASI)
A51: M011 | B51: MOM | C51: Oxytocin Stimulation Massage (Pijat Oksitosin) | D51: 30 | E51: 50000 | F51: 10 | G51: 5 | H51: YA | L51: =IFERROR(__xludf.DUMMYFUNCTION("""COMPUTED_VALUE"""),"Oxytocin Stimulation Massage (Pijat Oksitosin)") -> Oxytocin Stimulation Massage (Pijat Oksitosin)
A52: M012 | B52: MOM | C52: Basic Breast Care (Breast Care Tanpa Penyulit Laktasi) | D52: 30 | E52: 50000 | F52: 10 | G52: 5 | H52: YA | L52: =IFERROR(__xludf.DUMMYFUNCTION("""COMPUTED_VALUE"""),"Basic Breast Care (Breast Care Tanpa Penyulit Laktasi)") -> Basic Breast Care (Breast Care Tanpa Penyulit Laktasi)
A53: M013 | B53: MOM | C53: Advanced Breast Care (Breast Care Dengan Penyulit Laktasi) | D53: 45 | E53: 80000 | F53: 20 | G53: 10 | H53: YA | L53: =IFERROR(__xludf.DUMMYFUNCTION("""COMPUTED_VALUE"""),"Advanced Breast Care (Breast Care Dengan Penyulit Laktasi)") -> Advanced Breast Care (Breast Care Dengan Penyulit Laktasi)
A54: M009 | B54: MOM | C54: Foot Spa Therapy (Perawatan Foot Spa) | D54: 15 | E54: 40000 | F54: 10 | G54: 5 | H54: YA | L54: =IFERROR(__xludf.DUMMYFUNCTION("""COMPUTED_VALUE"""),"Foot Spa Therapy (Perawatan Foot Spa)") -> Foot Spa Therapy (Perawatan Foot Spa)
A55: HBK001 | B55: HOMECARE BABY KID | C55: Baby Relaxation Massage HC (Pijat Relaksasi Bayi) | D55: 40 | E55: 75000 | F55: 20 | G55: 5 | H55: YA | L55: =IFERROR(__xludf.DUMMYFUNCTION("""COMPUTED_VALUE"""),"Baby Relaxation Massage HC (Pijat Relaksasi Bayi)") -> Baby Relaxation Massage HC (Pijat Relaksasi Bayi)
A56: HBK002 | B56: HOMECARE BABY KID | C56: Kids Massage HC (Pijat Anak) | D56: 45 | E56: 80000 | F56: 35 | G56: 10 | H56: YA | L56: =IFERROR(__xludf.DUMMYFUNCTION("""COMPUTED_VALUE"""),"Kids Massage HC (Pijat Anak)") -> Kids Massage HC (Pijat Anak)
A57: HBK003 | B57: HOMECARE BABY KID | C57: Basic Baby Gym HC (Gym Bayi Dasar) | D57: 5 | E57: 20000 | F57: 5 | G57: 2 | H57: YA | L57: =IFERROR(__xludf.DUMMYFUNCTION("""COMPUTED_VALUE"""),"Basic Baby Gym HC (Gym Bayi Dasar)") -> Basic Baby Gym HC (Gym Bayi Dasar)
A58: HBK006 | B58: HOMECARE BABY KID | C58: Tuina Massage Baby/Kid HC (Pijat Tuina) | D58: 60 | E58: 90000 | F58: 35 | G58: 10 | H58: YA | L58: =IFERROR(__xludf.DUMMYFUNCTION("""COMPUTED_VALUE"""),"Tuina Massage Baby/Kid HC (Pijat Tuina)") -> Tuina Massage Baby/Kid HC (Pijat Tuina)
A59: HBK007 | B59: HOMECARE BABY KID | C59: Colic Relief Massage HC (Pijat Kolik) | D59: 60 | E59: 90000 | F59: 35 | G59: 10 | H59: YA | L59: =IFERROR(__xludf.DUMMYFUNCTION("""COMPUTED_VALUE"""),"Colic Relief Massage HC (Pijat Kolik)") -> Colic Relief Massage HC (Pijat Kolik)
A60: HBK008 | B60: HOMECARE BABY KID | C60: Cough & Cold Massage HC (Pijat Batuk & Pilek) | D60: 60 | E60: 90000 | F60: 35 | G60: 10 | H60: YA | L60: =IFERROR(__xludf.DUMMYFUNCTION("""COMPUTED_VALUE"""),"Cough & Cold Massage HC (Pijat Batuk & Pilek)") -> Cough & Cold Massage HC (Pijat Batuk & Pilek)
A61: HBK009 | B61: HOMECARE BABY KID | C61: Constipation Relief Massage HC (Pijat Konstipasi) | D61: 60 | E61: 90000 | F61: 35 | G61: 10 | H61: YA | L61: =IFERROR(__xludf.DUMMYFUNCTION("""COMPUTED_VALUE"""),"Constipation Relief Massage HC (Pijat Konstipasi)") -> Constipation Relief Massage HC (Pijat Konstipasi)
A62: HBK010 | B62: HOMECARE BABY KID | C62: Baby Ear Piercing HC (Tindik Telinga Bayi) | D62: 5 | E62: 50000 | F62: 10 | G62: 5 | H62: YA | L62: =IFERROR(__xludf.DUMMYFUNCTION("""COMPUTED_VALUE"""),"Baby Ear Piercing HC (Tindik Telinga Bayi)") -> Baby Ear Piercing HC (Tindik Telinga Bayi)
A63: HBK011 | B63: HOMECARE BABY KID | C63: Baby Nail Trimming HC (Pemotongan Kuku Bayi) | D63: 5 | E63: 20000 | F63: 5 | G63: 2 | H63: YA | L63: =IFERROR(__xludf.DUMMYFUNCTION("""COMPUTED_VALUE"""),"Baby Nail Trimming HC (Pemotongan Kuku Bayi)") -> Baby Nail Trimming HC (Pemotongan Kuku Bayi)
A64: HBK012 | B64: HOMECARE BABY KID | C64: Newborn Head Shaving HC (Cukur Gundul Bayi) | D64: 15 | E64: 50000 | F64: 10 | G64: 5 | H64: YA | L64: =IFERROR(__xludf.DUMMYFUNCTION("""COMPUTED_VALUE"""),"Newborn Head Shaving HC (Cukur Gundul Bayi)") -> Newborn Head Shaving HC (Cukur Gundul Bayi)
A65: HBK013 | B65: HOMECARE BABY KID | C65: Basic Personal Hygiene HC (Perawatan Kebersihan Dasar) | D65: 10 | E65: 20000 | F65: 5 | G65: 2 | H65: YA | L65: =IFERROR(__xludf.DUMMYFUNCTION("""COMPUTED_VALUE"""),"Basic Personal Hygiene HC (Perawatan Kebersihan Dasar)") -> Basic Personal Hygiene HC (Perawatan Kebersihan Dasar)
A66: HBK004 | B66: HOMECARE BABY KID | C66: Infrared Therapy HC (Terapi Infrared) | D66: 10 | E66: 50000 | F66: 10 | G66: 5 | H66: YA | L66: =IFERROR(__xludf.DUMMYFUNCTION("""COMPUTED_VALUE"""),"Infrared Therapy HC (Terapi Infrared)") -> Infrared Therapy HC (Terapi Infrared)
A67: HBK005 | B67: HOMECARE BABY KID | C67: Nebulizer Therapy HC (Terapi Nebulizer) | D67: 10 | E67: 50000 | F67: 10 | G67: 5 | H67: YA | L67: =IFERROR(__xludf.DUMMYFUNCTION("""COMPUTED_VALUE"""),"Nebulizer Therapy HC (Terapi Nebulizer)") -> Nebulizer Therapy HC (Terapi Nebulizer)
A68: HBK014 | B68: HOMECARE BABY KID | C68: Newborn Starter Pack With Piercing HC (Paket Awal Kehidupan) | D68: 70 | E68: 150000 | F68: 40 | G68: 10 | H68: YA | L68: =IFERROR(__xludf.DUMMYFUNCTION("""COMPUTED_VALUE"""),"Newborn Starter Pack With Piercing HC (Paket Awal Kehidupan)") -> Newborn Starter Pack With Piercing HC (Paket Awal Kehidupan)
A69: HBK015 | B69: HOMECARE BABY KID | C69: Newborn Starter Pack Without Piercing HC (Paket Awal Kehidupan) | D69: 70 | E69: 120000 | F69: 35 | G69: 10 | H69: YA | L69: =IFERROR(__xludf.DUMMYFUNCTION("""COMPUTED_VALUE"""),"Newborn Starter Pack Without Piercing HC (Paket Awal Kehidupan)") -> Newborn Starter Pack Without Piercing HC (Paket Awal Kehidupan)
A70: HBK016 | B70: HOMECARE BABY KID | C70: 1 Day New Born Pack HC | D70: 60 | E70: 125000 | F70: 35 | G70: 10 | H70: YA | L70: =IFERROR(__xludf.DUMMYFUNCTION("""COMPUTED_VALUE"""),"1 Day New Born Pack HC") -> 1 Day New Born Pack HC
A71: HBK017 | B71: HOMECARE BABY KID | C71: 3 Days New Born Pack HC | D71: 60 | E71: 395000 | F71: 105 | G71: 10 | H71: YA | L71: =IFERROR(__xludf.DUMMYFUNCTION("""COMPUTED_VALUE"""),"3 Days New Born Pack HC") -> 3 Days New Born Pack HC
A72: HBK018 | B72: HOMECARE BABY KID | C72: 7 Days New Born Pack HC | D72: 60 | E72: 800000 | F72: 245 | G72: 10 | H72: YA | L72: =IFERROR(__xludf.DUMMYFUNCTION("""COMPUTED_VALUE"""),"7 Days New Born Pack HC") -> 7 Days New Born Pack HC
A73: HBK019 | B73: HOMECARE BABY KID | C73: 1x Clear Breath Premium (Paket Nafas Lega) HC | D73: 60 | E73: 145000 | F73: 40 | G73: 10 | H73: YA | L73: =IFERROR(__xludf.DUMMYFUNCTION("""COMPUTED_VALUE"""),"1x Clear Breath Premium (Paket Nafas Lega) HC") -> 1x Clear Breath Premium (Paket Nafas Lega) HC
A74: HBK020 | B74: HOMECARE BABY KID | C74: 2x Clear Breath Premium (Paket Nafas Lega) HC | D74: 60 | E74: 250000 | F74: 80 | G74: 10 | H74: YA | L74: =IFERROR(__xludf.DUMMYFUNCTION("""COMPUTED_VALUE"""),"2x Clear Breath Premium (Paket Nafas Lega) HC") -> 2x Clear Breath Premium (Paket Nafas Lega) HC
A75: HBK021 | B75: HOMECARE BABY KID | C75: 1x Healthy Breath Package (Paket Nafas Sehat) HC | D75: 30 | E75: 60000 | F75: 10 | G75: 5 | H75: YA | L75: =IFERROR(__xludf.DUMMYFUNCTION("""COMPUTED_VALUE"""),"1x Healthy Breath Package (Paket Nafas Sehat) HC") -> 1x Healthy Breath Package (Paket Nafas Sehat) HC
A76: HBK022 | B76: HOMECARE BABY KID | C76: 2x Healthy Breath Package (Paket Nafas Sehat) HC | D76: 30 | E76: 100000 | F76: 35 | G76: 10 | H76: YA | L76: =IFERROR(__xludf.DUMMYFUNCTION("""COMPUTED_VALUE"""),"2x Healthy Breath Package (Paket Nafas Sehat) HC") -> 2x Healthy Breath Package (Paket Nafas Sehat) HC
A77: HM001 | B77: HOMECARE MOM | C77: Prenatal Wellness Massage HC (Pijat Prenatal) | D77: 70 | E77: 150000 | F77: 40 | G77: 10 | H77: YA | L77: =IFERROR(__xludf.DUMMYFUNCTION("""COMPUTED_VALUE"""),"Prenatal Wellness Massage HC (Pijat Prenatal)") -> Prenatal Wellness Massage HC (Pijat Prenatal)
A78: HM002 | B78: HOMECARE MOM | C78: Facial Acupressure & Mask HC (Totok Wajah & Masker Wajah) | D78: 20 | E78: 40000 | F78: 10 | G78: 5 | H78: YA | L78: =IFERROR(__xludf.DUMMYFUNCTION("""COMPUTED_VALUE"""),"Facial Acupressure & Mask HC (Totok Wajah & Masker Wajah)") -> Facial Acupressure & Mask HC (Totok Wajah & Masker Wajah)
A79: HM004 | B79: HOMECARE MOM | C79: Back & Arms Relaxation Massage HC (Pijat Relaksasi Punggung & Tangan) | D79: 15 | E79: 65000 | F79: 20 | G79: 5 | H79: YA | L79: =IFERROR(__xludf.DUMMYFUNCTION("""COMPUTED_VALUE"""),"Back & Arms Relaxation Massage HC (Pijat Relaksasi Punggung & Tangan)") -> Back & Arms Relaxation Massage HC (Pijat Relaksasi Punggung & Tangan)
A80: HM003 | B80: HOMECARE MOM | C80: Foot Spa Therapy HC (Perawatan Foot Spa) | D80: 30 | E80: 40000 | F80: 10 | G80: 5 | H80: YA | L80: =IFERROR(__xludf.DUMMYFUNCTION("""COMPUTED_VALUE"""),"Foot Spa Therapy HC (Perawatan Foot Spa)") -> Foot Spa Therapy HC (Perawatan Foot Spa)
A81: HM005 | B81: HOMECARE MOM | C81: Early Pregnancy Revitalization Package HC (Perawatan Awal Kehamilan) | D81: 60 | E81: 95000 | F81: 35 | G81: 10 | H81: YA | L81: =IFERROR(__xludf.DUMMYFUNCTION("""COMPUTED_VALUE"""),"Early Pregnancy Revitalization Package HC (Perawatan Awal Kehamilan)") -> Early Pregnancy Revitalization Package HC (Perawatan Awal Kehamilan)
A82: HM006 | B82: HOMECARE MOM | C82: Mid-Pregnancy Wellness Package HC (Perawatan Tengah Kehamilan) | D82: 45 | E82: 185000 | F82: 40 | G82: 10 | H82: YA | L82: =IFERROR(__xludf.DUMMYFUNCTION("""COMPUTED_VALUE"""),"Mid-Pregnancy Wellness Package HC (Perawatan Tengah Kehamilan)") -> Mid-Pregnancy Wellness Package HC (Perawatan Tengah Kehamilan)
A83: HM007 | B83: HOMECARE MOM | C83: Postnatal Recovery Massage HC (Pijat Pemulihan Pascapersalinan) | D83: 70 | E83: 150000 | F83: 40 | G83: 10 | H83: YA | L83: =IFERROR(__xludf.DUMMYFUNCTION("""COMPUTED_VALUE"""),"Postnatal Recovery Massage HC (Pijat Pemulihan Pascapersalinan)") -> Postnatal Recovery Massage HC (Pijat Pemulihan Pascapersalinan)
A84: HM008 | B84: HOMECARE MOM | C84: Platinum Recovery Package HC (Paket Platinum Pascapersalinan) | D84: 100 | E84: 190000 | F84: 50 | G84: 10 | H84: YA | L84: =IFERROR(__xludf.DUMMYFUNCTION("""COMPUTED_VALUE"""),"Platinum Recovery Package HC (Paket Platinum Pascapersalinan)") -> Platinum Recovery Package HC (Paket Platinum Pascapersalinan)
A85: HM010 | B85: HOMECARE MOM | C85: Lactation Support Package HC (Paket Lancar ASI) | D85: 80 | E85: 90000 | F85: 35 | G85: 10 | H85: YA | L85: =IFERROR(__xludf.DUMMYFUNCTION("""COMPUTED_VALUE"""),"Lactation Support Package HC (Paket Lancar ASI)") -> Lactation Support Package HC (Paket Lancar ASI)
A86: HM011 | B86: HOMECARE MOM | C86: Oxytocin Stimulation Massage HC (Pijat Oksitosin) | D86: 30 | E86: 50000 | F86: 10 | G86: 5 | H86: YA | L86: =IFERROR(__xludf.DUMMYFUNCTION("""COMPUTED_VALUE"""),"Oxytocin Stimulation Massage HC (Pijat Oksitosin)") -> Oxytocin Stimulation Massage HC (Pijat Oksitosin)
A87: HM012 | B87: HOMECARE MOM | C87: Basic Breast Care HC (Breast Care Tanpa Penyulit Laktasi) | D87: 30 | E87: 50000 | F87: 10 | G87: 5 | H87: YA | L87: =IFERROR(__xludf.DUMMYFUNCTION("""COMPUTED_VALUE"""),"Basic Breast Care HC (Breast Care Tanpa Penyulit Laktasi)") -> Basic Breast Care HC (Breast Care Tanpa Penyulit Laktasi)
A88: HM013 | B88: HOMECARE MOM | C88: Advanced Breast Care HC (Breast Care Dengan Penyulit Laktasi) | D88: 45 | E88: 90000 | F88: 20 | G88: 10 | H88: YA | L88: =IFERROR(__xludf.DUMMYFUNCTION("""COMPUTED_VALUE"""),"Advanced Breast Care HC (Breast Care Dengan Penyulit Laktasi)") -> Advanced Breast Care HC (Breast Care Dengan Penyulit Laktasi)
A89: HM009 | B89: HOMECARE MOM | C89: Foot Spa Therapy HC (Perawatan Foot Spa) | D89: 15 | E89: 40000 | F89: 10 | G89: 5 | H89: YA | L89: =IFERROR(__xludf.DUMMYFUNCTION("""COMPUTED_VALUE"""),"Foot Spa Therapy HC (Perawatan Foot Spa)") -> Foot Spa Therapy HC (Perawatan Foot Spa)
A90: HM014 | B90: HOMECARE MOM | C90: 1 Day Recovery Mom Package HC | D90: 90 | E90: 125000 | F90: 35 | G90: 10 | H90: YA | L90: =IFERROR(__xludf.DUMMYFUNCTION("""COMPUTED_VALUE"""),"1 Day Recovery Mom Package HC") -> 1 Day Recovery Mom Package HC
A91: HM015 | B91: HOMECARE MOM | C91: 3 Days Recovery Mom Package HC | D91: 90 | E91: 370000 | F91: 105 | G91: 10 | H91: YA | L91: =IFERROR(__xludf.DUMMYFUNCTION("""COMPUTED_VALUE"""),"3 Days Recovery Mom Package HC") -> 3 Days Recovery Mom Package HC
A92: HM016 | B92: HOMECARE MOM | C92: 7 Days Recovery Mom Package HC | D92: 90 | E92: 800000 | F92: 245 | G92: 10 | H92: YA | L92: =IFERROR(__xludf.DUMMYFUNCTION("""COMPUTED_VALUE"""),"7 Days Recovery Mom Package HC") -> 7 Days Recovery Mom Package HC

Sheet MASTER_TERAPIS
A1: therapist_code | B1: therapist_name | C1: specialty | D1: active | E1: homecare_available | F1: transport_bonus | G1: notes
A2: T001 | B2: bababab | D2: YA | E2: YA | F2: 0 | I2: =IFERROR(__xludf.DUMMYFUNCTION("ifna(FILTER(MASTER_TERAPIS!B2:B1000, MASTER_TERAPIS!D2:D1000 = ""Ya""),0)"),"bababab") -> bababab | K2: Update Terapis
A3: T002 | B3: Caccaca | D3: YA | E3: YA | F3: 0 | I3: =IFERROR(__xludf.DUMMYFUNCTION("""COMPUTED_VALUE"""),"Caccaca") -> Caccaca
A4: T003 | B4: ggagaga | D4: YA | E4: YA | F4: 0 | I4: =IFERROR(__xludf.DUMMYFUNCTION("""COMPUTED_VALUE"""),"ggagaga") -> ggagaga
A5: T004 | B5: hahaha | D5: YA | E5: YA | F5: 0 | I5: =IFERROR(__xludf.DUMMYFUNCTION("""COMPUTED_VALUE"""),"hahaha") -> hahaha

Sheet MASTER_SA
A1: SA_code | B1: SA_name | C1: active | D1: notes
A2: S001 | B2: fhfhfhf | C2: YA | F2: =IFERROR(__xludf.DUMMYFUNCTION("ifna(FILTER(MASTER_SA!B2:B1000, MASTER_SA!C2:C1000 = ""Ya""),0)"),"fhfhfhf") -> fhfhfhf | H2: Update SA
A3: S002 | B3: fkakaka | C3: TIDAK
C4: TIDAK
C5: TIDAK

Sheet MASTER_HOMECARE
A1: area_name | B1: distance_label | C1: transport_fee | D1: active | E1: notes
A2: NONE | D2: YA
A3: Zona Dekat | B3: 0-5 KM | C3: 15000 | D3: YA
A4: Zona Sedang | B4: 5-10 KM | C4: 25000 | D4: YA
A5: Zona Jauh | B5: >10 KM | C5: 40000 | D5: YA

Sheet MASTER_PROMO
A1: promo_code | B1: promo_name | C1: promo_type | D1: promo_value | E1: start_date | F1: end_date | G1: active
A2: NONE | B2: Tidak Ada | C2: NOMINAL | D2: 0 | G2: YA
A3: PROMO10 | B3: Promo 10% | C3: PERCENT | D3: 10 | G3: YA
A4: PROMO20 | B4: Promo 20% | C4: PERCENT | D4: 20 | G4: YA
A5: POT25K | B5: Potongan 25.000 | C5: NOMINAL | D5: 25000 | G5: YA
A6: POT50K | B6: Potongan 50.000 | C6: NOMINAL | D6: 50000 | G6: YA

Sheet MASTER_JENIS_PELANGGAN
A1: customer_type | B1: min_visit | C1: max_visit | D1: notes
A2: Baru | B2: 1 | C2: 1 | D2: Otomatis jika visit_count = 1
A3: Repeat | B3: 2 | C3: 10 | D3: Otomatis jika visit_count 2-10
A4: VIP | B4: 11 | D4: Otomatis jika visit_count > 10

Sheet MASTER_TANGGAL
A1: Tgl | B1: Bln | C1: Tahun
A2: 1 | B2: 1 | C2: 2026
A3: 2 | B3: 2 | C3: 2027
A4: 3 | B4: 3 | C4: 2028
A5: 4 | B5: 4 | C5: 2029
A6: 5 | B6: 5 | C6: 2030
A7: 6 | B7: 6 | C7: 2031
A8: 7 | B8: 7 | C8: 2032
A9: 8 | B9: 8 | C9: 2033
A10: 9 | B10: 9 | C10: 2034
A11: 10 | B11: 10
A12: 11 | B12: 11
A13: 12 | B13: 12
A14: 13
A15: 14
A16: 15
A17: 16
A18: 17
A19: 18
A20: 19
A21: 20
A22: 21
A23: 22
A24: 23
A25: 24
... A32: 31

Sheet VALIDATION
A1: LIST_BOOKING_TYPE | B1: LIST_STATUS_INPUT | C1: LIST_SERVICE | D1: LIST_THERAPIST | E1: LIST_PAYMENT | F1: LIST_AREA | G1: LIST_PROMO | H1: LIST_TIME | I1: LIST_CUSTOMER_TYPE | J1: LIST_PAYMENT_STATUS | K1: LIST_RECORD_STATUS | L1: LIST_BOOKING_STATUS_LOG
A2: Inhouse | C2: BABY | D2: April | E2: Tunai | F2: 0-5 KM | G2: Tidak Ada | H2: 08:00 | I2: Baru | J2: Belum Bayar | K2: Active
A3: Homecare | B3: Cancelled | C3: BABY | D3: Ulya | E3: Transfer | F3: 5-10 KM | G3: Promo 10% | H3: 08:05 | I3: Repeat | J3: DP | K3: Archived | L3: Cancelled
C4: BABY | D4: Salsa | E4: QRIS | F4: >10 KM | G4: Promo 20% | H4: 08:10 | I4: VIP | J4: Lunas | L4: Done
C5: BABY | D5: Owner | G5: Potongan 25.000 | H5: 08:15
C6: BABY | G6: Potongan 50.000 | H6: 08:20
C7: BABY | H7: 08:25
C8: BABY | H8: 08:30
C9: BABY | H9: 08:35
C10: BABY | H10: 08:40
C11: BABY | H11: 08:45
C12: BABY | H12: 08:50
C13: BABY | H13: 08:55
C14: BABY | H14: 09:00
C15: BABY | H15: 09:05
C16: BABY | H16: 09:10
C17: BABY | H17: 09:15
C18: BABY | H18: 09:20
... C92: HOMECARE MOM | H92: 15:30
H93: 15:35
H94: 15:40
H95: 15:45
H96: 15:50
H97: 15:55
H98: 16:00
H99: 16:05
H100: 16:10
H101: 16:15
H102: 16:20
H103: 16:25
H104: 16:30
... H146: 20:00

Sheet SETTING
A1: SETTING SMARTSPADASH PRO
A3: setting_key | B3: setting_value | C3: notes | E3: email | F3: role
A4: clinic_name | B4: SmartSpaDash Demo | C4: Ubah sesuai klinik | E4: owner@contoh.com | F4: OWNER
A5: tagline | B5: All-in-One Booking System Mom Baby Spa | E5: admin@contoh.com | F5: ADMIN
A6: theme_name | B6: Sage Luxury | C6: Soft Rose / Sage Luxury
A7: system_mode | B7: LIVE | C7: LIVE / DEMO
A8: opening_hour | B8: 08:00
A9: closing_hour | B9: 20:00
A10: booking_interval | B10: 5 | C10: menit
A11: default_booking_status | B11: Draft
A12: transport_0_5 | B12: 15000
A13: transport_5_10 | B13: 25000
A14: transport_gt_10 | B14: 35000

Sheet BANTUAN
A1: BANTUAN & FAQ
A3: Bagaimana input booking? | B3: Buka INPUT BOOKING, isi field wajib, lalu gunakan menu SmartSpaDash > Simpan Booking.
A4: Bagaimana cek bentrok? | B4: Isi tanggal, jam, dan terapis lalu gunakan menu SmartSpaDash > Cek Bentrok.
A5: Bagaimana cari pelanggan lama? | B5: Isi nomor WA pada INPUT BOOKING lalu gunakan menu SmartSpaDash > Cari Pelanggan.
A6: Bagaimana tandai done? | B6: Gunakan menu SmartSpaDash > Tandai Selesai (Done).
A7: Bagaimana buat invoice? | B7: Gunakan menu SmartSpaDash > Buat Invoice dari booking yang tersimpan.

Sheet SYSTEM LOG
A1: timestamp | B1: actor_email | C1: actor_role | D1: action | E1: booking_id | F1: target_sheet | G1: target_row | H1: old_value | I1: new_value | J1: details
A2: 46105.259 | B2: puguh.legowo.k@gmail.com | C2: OWNER | D2: LOGIN_OK | F2: LOGIN | J2: Login berhasil.
A3: 46105.26 | B3: puguh.legowo.k@gmail.com | C3: OWNER | D3: LOGOUT | F3: LOGIN | J3: Logout manual.
A4: 46105.261 | B4: puguh.legowo.k@gmail.com | C4: OWNER | D4: LOGIN_OK | F4: LOGIN | J4: Login berhasil.
A5: 46105.301 | B5: puguh.legowo.k@gmail.com | C5: OWNER | D5: SAVE_BOOKING | E5: BK-20260324-001 | F5: TRANSAKSI_LOG | G5: 6 | I5: {"booking_status":"Active","payment_status":"Belum Bayar","service_done_status":"PENDING"} | J5: Booking baru tersimpan dari INPUT BOOKING.
A6: 46104.852 | B6: puguh.legowo.k@gmail.com | C6: OWNER | D6: LOGIN_OK | F6: LOGIN | J6: Login berhasil.
A7: 46104.853 | B7: puguh.legowo.k@gmail.com | C7: OWNER | D7: MARK_PAID | E7: BK-20260324-001 | F7: TRANSAKSI_LOG | G7: 6 | H7: {"payment_status":"Belum Bayar","remaining_balance":75000} | I7: {"payment_status":"Lunas","remaining_balance":0} | J7: Pelunasan manual berbasis kode booking.
A8: 46104.853 | B8: puguh.legowo.k@gmail.com | C8: OWNER | D8: MARK_SESSION_DONE | E8: BK-20260324-001 | F8: TRANSAKSI_LOG | G8: 6 | H8: {"booking_status":"Active","service_done_status":"Pending","payment_status":"Lunas"} | I8: {"booking_status":"Done","service_done_status":"DONE","payment_status":"Lunas"} | J8: Sesi selesai diproses berbasis kode booking.
A9: 46104.854 | B9: puguh.legowo.k@gmail.com | C9: OWNER | D9: SAVE_BOOKING | E9: BK-20260324-001 | F9: TRANSAKSI_LOG | G9: 7 | I9: {"booking_status":"Active","payment_status":"Belum Bayar","service_done_status":"PENDING"} | J9: Booking baru tersimpan dari INPUT BOOKING.
A10: 46104.854 | B10: puguh.legowo.k@gmail.com | C10: OWNER | D10: SAVE_BOOKING | E10: BK-20260324-002 | F10: TRANSAKSI_LOG | G10: 2 | I10: {"booking_status":"Active","payment_status":"Belum Bayar","service_done_status":"PENDING"} | J10: Booking baru tersimpan dari INPUT BOOKING.
A11: 46104.855 | B11: puguh.legowo.k@gmail.com | C11: OWNER | D11: SAVE_BOOKING | E11: BK-20260324-003 | F11: TRANSAKSI_LOG | G11: 3 | I11: {"booking_status":"Active","payment_status":"Belum Bayar","service_done_status":"PENDING"} | J11: Booking baru tersimpan dari INPUT BOOKING.
A12: 46104.856 | B12: puguh.legowo.k@gmail.com | C12: OWNER | D12: MARK_SESSION_DONE | E12: BK-20260324-002 | F12: TRANSAKSI_LOG | G12: 2 | H12: {"booking_status":"Active","service_done_status":"PENDING","payment_status":"Belum Bayar"} | I12: {"booking_status":"Done","service_done_status":"DONE","payment_status":"Belum Bayar"} | J12: Sesi selesai diproses berbasis kode booking.
A13: 46104.856 | B13: puguh.legowo.k@gmail.com | C13: OWNER | D13: MARK_PAID | E13: BK-20260324-002 | F13: TRANSAKSI_LOG | G13: 2 | H13: {"payment_status":"Belum Bayar","remaining_balance":85000} | I13: {"payment_status":"Lunas","remaining_balance":0} | J13: Pelunasan manual berbasis kode booking.
A14: 46104.856 | B14: puguh.legowo.k@gmail.com | C14: OWNER | D14: MARK_SESSION_DONE | E14: BK-20260324-002 | F14: TRANSAKSI_LOG | G14: 2 | H14: {"booking_status":"Done","service_done_status":"DONE","payment_status":"Lunas"} | I14: {"booking_status":"Done","service_done_status":"DONE","payment_status":"Lunas"} | J14: Sesi selesai diproses berbasis kode booking.
A15: 46104.857 | B15: puguh.legowo.k@gmail.com | C15: OWNER | D15: CRM_FAVORITE_REFRESH | F15: CRM PELANGGAN | J15: favorite_service dihitung ulang dari layanan tersering.
A16: 46104.869 | B16: puguh.legowo.k@gmail.com | C16: OWNER | D16: MARK_PAID | E16: BK-20260324-003 | F16: TRANSAKSI_LOG | G16: 3 | H16: {"payment_status":"Belum Bayar","remaining_balance":90000} | I16: {"payment_status":"Lunas","remaining_balance":0} | J16: Pelunasan manual berbasis kode booking.
A17: 46104.869 | B17: puguh.legowo.k@gmail.com | C17: OWNER | D17: MARK_SESSION_DONE | E17: BK-20260324-003 | F17: TRANSAKSI_LOG | G17: 3 | H17: {"booking_status":"Active","service_done_status":"PENDING","payment_status":"Lunas"} | I17: {"booking_status":"Done","service_done_status":"DONE","payment_status":"Lunas"} | J17: Sesi selesai diproses berbasis kode booking.
A18: 46105.828 | B18: puguh.legowo.k@gmail.com | C18: OWNER | D18: LOGIN_OK | F18: LOGIN | J18: Login berhasil.
A19: 46105.829 | B19: puguh.legowo.k@gmail.com | C19: OWNER | D19: SAVE_BOOKING | E19: BK-20260325-001 | F19: TRANSAKSI_LOG | G19: 4 | I19: {"booking_status":"Active","payment_status":"Belum Bayar","service_done_status":"PENDING"} | J19: Booking baru tersimpan dari INPUT BOOKING.
A20: 46105.834 | B20: puguh.legowo.k@gmail.com | C20: OWNER | D20: SAVE_BOOKING | E20: BK-20260325-002 | F20: TRANSAKSI_LOG | G20: 5 | I20: {"booking_status":"Active","payment_status":"Belum Bayar","service_done_status":"PENDING"} | J20: Booking baru tersimpan dari INPUT BOOKING.
A21: 46105.835 | B21: puguh.legowo.k@gmail.com | C21: OWNER | D21: MARK_PAID | E21: BK-20260325-002 | F21: TRANSAKSI_LOG | G21: 5 | H21: {"payment_status":"Belum Bayar","remaining_balance":150000} | I21: {"payment_status":"Lunas","remaining_balance":0} | J21: Pelunasan manual berbasis hasil pencarian booking.
A22: 46105.835 | B22: puguh.legowo.k@gmail.com | C22: OWNER | D22: MARK_SESSION_DONE | E22: BK-20260325-002 | F22: TRANSAKSI_LOG | G22: 5 | H22: {"booking_status":"Active","service_done_status":"PENDING","payment_status":"Lunas"} | I22: {"booking_status":"Done","service_done_status":"DONE","payment_status":"Lunas"} | J22: Sesi selesai diproses berbasis hasil pencarian booking.
A23: 46105.872 | B23: puguh.legowo.k@gmail.com | C23: OWNER | D23: LOGIN_OK | F23: LOGIN | J23: Login berhasil.
A24: 46105.898 | B24: puguh.legowo.k@gmail.com | C24: OWNER | D24: SAVE_BOOKING | E24: BK-20260325-001 | F24: TRANSAKSI_LOG | G24: 2 | I24: {"booking_status":"Active","payment_status":"Belum Bayar","service_done_status":"PENDING"} | J24: Booking baru tersimpan dari INPUT BOOKING.
A25: 46105.901 | B25: puguh.legowo.k@gmail.com | C25: OWNER | D25: SAVE_BOOKING | E25: BK-20260325-002 | F25: TRANSAKSI_LOG | G25: 3 | I25: {"booking_status":"Active","payment_status":"Belum Bayar","service_done_status":"PENDING"} | J25: Booking baru tersimpan dari INPUT BOOKING.
A26: 46105.902 | B26: puguh.legowo.k@gmail.com | C26: OWNER | D26: SAVE_BOOKING | E26: BK-20260325-003 | F26: TRANSAKSI_LOG | G26: 4 | I26: {"booking_status":"Active","payment_status":"Belum Bayar","service_done_status":"PENDING"} | J26: Booking baru tersimpan dari INPUT BOOKING.
A27: 46105.905 | B27: puguh.legowo.k@gmail.com | C27: OWNER | D27: MARK_PAID | E27: BK-20260325-001 | F27: TRANSAKSI_LOG | G27: 2 | H27: {"payment_status":"Belum Bayar","remaining_balance":150000} | I27: {"payment_status":"Lunas","remaining_balance":0} | J27: Pelunasan manual berbasis hasil pencarian booking.
A28: 46105.905 | B28: puguh.legowo.k@gmail.com | C28: OWNER | D28: MARK_SESSION_DONE | E28: BK-20260325-001 | F28: TRANSAKSI_LOG | G28: 2 | H28: {"booking_status":"Active","service_done_status":"PENDING","payment_status":"Lunas"} | I28: {"booking_status":"Done","service_done_status":"DONE","payment_status":"Lunas"} | J28: Sesi selesai diproses berbasis hasil pencarian booking.
A29: 46105.905 | B29: puguh.legowo.k@gmail.com | C29: OWNER | D29: MARK_SESSION_DONE | E29: BK-20260325-001 | F29: TRANSAKSI_LOG | G29: 2 | H29: {"booking_status":"Done","service_done_status":"DONE","payment_status":"Lunas"} | I29: {"booking_status":"Done","service_done_status":"DONE","payment_status":"Lunas"} | J29: Sesi selesai diproses berbasis hasil pencarian booking.
A30: 46106.825 | B30: puguh.legowo.k@gmail.com | C30: OWNER | D30: LOGIN_OK | F30: LOGIN | J30: Login berhasil.
A31: 46107.355 | B31: puguh.legowo.k@gmail.com | C31: OWNER | D31: LOGIN_OK | F31: LOGIN | J31: Login berhasil.
A32: 46107.355 | B32: puguh.legowo.k@gmail.com | C32: OWNER | D32: MARK_PAID | E32: BK-20260325-002 | F32: TRANSAKSI_LOG | G32: 3 | H32: {"payment_status":"Belum Bayar","remaining_balance":75000} | I32: {"payment_status":"Lunas","remaining_balance":0} | J32: Pelunasan manual berbasis hasil pencarian booking.
A33: 46107.355 | B33: puguh.legowo.k@gmail.com | C33: OWNER | D33: MARK_SESSION_DONE | E33: BK-20260325-002 | F33: TRANSAKSI_LOG | G33: 3 | H33: {"booking_status":"Active","service_done_status":"PENDING","payment_status":"Lunas"} | I33: {"booking_status":"Done","service_done_status":"DONE","payment_status":"Lunas"} | J33: Sesi selesai diproses berbasis hasil pencarian booking.
A34: 46107.356 | B34: puguh.legowo.k@gmail.com | C34: OWNER | D34: CRM_FAVORITE_REFRESH | F34: CRM PELANGGAN | J34: favorite_service dihitung ulang dari layanan tersering.
A35: 46107.357 | B35: puguh.legowo.k@gmail.com | C35: OWNER | D35: MARK_PAID | E35: BK-20260325-003 | F35: TRANSAKSI_LOG | G35: 4 | H35: {"payment_status":"Belum Bayar","remaining_balance":60000} | I35: {"payment_status":"Lunas","remaining_balance":0} | J35: Pelunasan manual berbasis hasil pencarian booking.
A36: 46107.358 | B36: puguh.legowo.k@gmail.com | C36: OWNER | D36: MARK_SESSION_DONE | E36: BK-20260325-003 | F36: TRANSAKSI_LOG | G36: 4 | H36: {"booking_status":"Active","service_done_status":"PENDING","payment_status":"Lunas"} | I36: {"booking_status":"Done","service_done_status":"DONE","payment_status":"Lunas"} | J36: Sesi selesai diproses berbasis hasil pencarian booking.
A37: 46107.359 | B37: puguh.legowo.k@gmail.com | C37: OWNER | D37: LOGOUT | F37: LOGIN | J37: Logout manual.
A38: 46107.427 | B38: puguh.legowo.k@gmail.com | C38: OWNER | D38: LOGIN_OK | F38: LOGIN | J38: Login berhasil.
A39: 46107.427 | B39: puguh.legowo.k@gmail.com | C39: OWNER | D39: REVERT_STATUS | E39: BK-20260325-003 | F39: TRANSAKSI_LOG | G39: 4 | H39: {"payment_status":"Lunas","booking_status":"Done","service_done_status":"DONE","remaining_balance":0} | I39: {"payment_status":"Belum Bayar","booking_status":"Active","service_done_status":"PENDING","remaining_balance":60000} | J39: Status booking dikembalikan dari hasil pencarian K6:K17.
A40: 46107.428 | B40: puguh.legowo.k@gmail.com | C40: OWNER | D40: MARK_PAID | E40: BK-20260325-003 | F40: TRANSAKSI_LOG | G40: 4 | H40: {"payment_status":"Belum Bayar","remaining_balance":60000} | I40: {"payment_status":"Lunas","remaining_balance":0} | J40: Pelunasan manual berbasis hasil pencarian booking.
A41: 46107.428 | B41: puguh.legowo.k@gmail.com | C41: OWNER | D41: MARK_SESSION_DONE | E41: BK-20260325-003 | F41: TRANSAKSI_LOG | G41: 4 | H41: {"booking_status":"Active","service_done_status":"PENDING","payment_status":"Lunas"} | I41: {"booking_status":"Done","service_done_status":"DONE","payment_status":"Lunas"} | J41: Sesi selesai diproses berbasis hasil pencarian booking.
A42: 46107.78 | B42: puguh.legowo.k@gmail.com | C42: OWNER | D42: LOGOUT | F42: LOGIN | J42: Logout manual.
A43: 46107.78 | B43: puguh.legowo.k@gmail.com | C43: OWNER | D43: LOGIN_OK | F43: LOGIN | J43: Login berhasil.
A44: 46107.781 | B44: puguh.legowo.k@gmail.com | C44: OWNER | D44: SAVE_BOOKING | E44: BK-20260326-004 | F44: TRANSAKSI_LOG | G44: 5 | I44: {"booking_status":"Active","payment_status":"Belum Bayar","service_done_status":"PENDING"} | J44: Booking baru tersimpan dari INPUT BOOKING.
A45: 46107.781 | B45: puguh.legowo.k@gmail.com | C45: OWNER | D45: MARK_PAID | E45: BK-20260325-003 | F45: TRANSAKSI_LOG | G45: 4 | H45: {"payment_status":"Lunas","remaining_balance":0} | I45: {"payment_status":"Lunas","remaining_balance":0} | J45: Pelunasan manual berbasis hasil pencarian booking.
A46: 46107.782 | B46: puguh.legowo.k@gmail.com | C46: OWNER | D46: MARK_SESSION_DONE | E46: BK-20260325-003 | F46: TRANSAKSI_LOG | G46: 4 | H46: {"booking_status":"Done","service_done_status":"DONE","payment_status":"Lunas"} | I46: {"booking_status":"Done","service_done_status":"DONE","payment_status":"Lunas"} | J46: Sesi selesai diproses berbasis hasil pencarian booking.
A47: 46107.782 | B47: puguh.legowo.k@gmail.com | C47: OWNER | D47: MARK_PAID | E47: BK-20260326-004 | F47: TRANSAKSI_LOG | G47: 5 | H47: {"payment_status":"Belum Bayar","remaining_balance":85000} | I47: {"payment_status":"Lunas","remaining_balance":0} | J47: Pelunasan manual berbasis hasil pencarian booking.
A48: 46107.783 | B48: puguh.legowo.k@gmail.com | C48: OWNER | D48: MARK_SESSION_DONE | E48: BK-20260326-004 | F48: TRANSAKSI_LOG | G48: 5 | H48: {"booking_status":"Active","service_done_status":"PENDING","payment_status":"Lunas"} | I48: {"booking_status":"Done","service_done_status":"DONE","payment_status":"Lunas"} | J48: Sesi selesai diproses berbasis hasil pencarian booking.

Sheet DASHBOARD V2 DATA
A1: Rank | B1: Layanan | C1: Category | D1: Inhouse/Homecare | E1: Jumlah Booking | G1: Periode | H1: Omzet Closed | K1: Periode | L1: Booking Closed | O1: Jenis | P1: Jumlah | S1: Total Booking Closed | T1: Omzet Closed | U1: Homecare Closed | V1: Inhouse Closed | W1: Avg Ticket Closed | Y1: Year Filter
A2: 1 | B2: Colic Relief Massage Baby (Pijat Kolik) | C2: BABY | D2: Inhouse | E2: 1 | G2: 46106 | H2: 285000 | K2: 46106 | L2: 3 | O2: Homecare | P2: 1 | S2: 4 | T2: 370000 | U2: 1 | V2: 3 | W2: 92500 | Y2: Semua Tahun
A3: 2 | B3: Healthy Breath Package (Paket Nafas Sehat) | C3: BABY | D3: Inhouse | E3: 1 | G3: 46107 | H3: 85000 | K3: 46107 | L3: 1 | O3: Inhouse | P3: 3 | Y3: 2026
A4: 3 | B4: Newborn Starter Pack With Piercing (Paket Awal Kehidupan) | C4: BABY | D4: Inhouse | E4: 1
A5: 4 | B5: Oxytocin Stimulation Massage HC (Pijat Oksitosin) | C5: HOMECARE MOM | D5: Homecare | E5: 1
